[{"id":"0","data":[{"section":"0-9","female":{"amount":123644,"percentage":8.4},"male":{"amount":184596,"percentage":12.5},"period":"חודש אחרון","order_period":5},{"section":"0-9","female":{"amount":246781,"percentage":9},"male":{"amount":327405,"percentage":11.9},"period":"שנה","order_period":2},{"section":"0-9","female":{"amount":221509,"percentage":8.9},"male":{"amount":297707,"percentage":11.9},"period":"6 חודשים","order_period":3},{"section":"0-9","female":{"amount":173157,"percentage":8},"male":{"amount":242047,"percentage":11.2},"period":"3 חודשים","order_period":4},{"section":"0-9","female":{"amount":293012,"percentage":8.4},"male":{"amount":383652,"percentage":11},"period":"מתחילת קורונה","order_period":1},{"section":"10-19","male":{"amount":303273,"percentage":11},"female":{"amount":281504,"percentage":10.3},"period":"שנה","order_period":2},{"section":"10-19","male":{"amount":238722,"percentage":11.1},"female":{"amount":218592,"percentage":10.1},"period":"3 חודשים","order_period":4},{"section":"10-19","male":{"amount":163556,"percentage":11.1},"female":{"amount":138455,"percentage":9.4},"period":"חודש אחרון","order_period":5},{"section":"10-19","male":{"amount":389584,"percentage":11.2},"female":{"amount":354491,"percentage":10.2},"period":"מתחילת קורונה","order_period":1},{"section":"10-19","male":{"amount":278014,"percentage":11.1},"female":{"amount":257792,"percentage":10.3},"period":"6 חודשים","order_period":3},{"section":"20-29","female":{"amount":205317,"percentage":8.2},"male":{"amount":137297,"percentage":5.5},"period":"6 חודשים","order_period":3},{"section":"20-29","female":{"amount":114476,"percentage":7.7},"male":{"amount":72802,"percentage":4.9},"period":"חודש אחרון","order_period":5},{"section":"20-29","female":{"amount":225759,"percentage":8.2},"male":{"amount":152993,"percentage":5.6},"period":"שנה","order_period":2},{"section":"20-29","female":{"amount":178014,"percentage":8.3},"male":{"amount":116864,"percentage":5.4},"period":"3 חודשים","order_period":4},{"section":"20-29","female":{"amount":298925,"percentage":8.6},"male":{"amount":217744,"percentage":6.3},"period":"מתחילת קורונה","order_period":1},{"section":"30-39","male":{"amount":122142,"percentage":5.7},"female":{"amount":190078,"percentage":8.8},"period":"3 חודשים","order_period":4},{"section":"30-39","male":{"amount":156632,"percentage":5.7},"female":{"amount":238460,"percentage":8.7},"period":"שנה","order_period":2},{"section":"30-39","male":{"amount":141929,"percentage":5.7},"female":{"amount":219170,"percentage":8.8},"period":"6 חודשים","order_period":3},{"section":"30-39","male":{"amount":83731,"percentage":5.7},"female":{"amount":133300,"percentage":9},"period":"חודש אחרון","order_period":5},{"section":"30-39","male":{"amount":204030,"percentage":5.9},"female":{"amount":292553,"percentage":8.4},"period":"מתחילת קורונה","order_period":1},{"section":"40-49","male":{"amount":78485,"percentage":5.3},"female":{"amount":118144,"percentage":8},"period":"חודש אחרון","order_period":5},{"section":"40-49","male":{"amount":141778,"percentage":5.2},"female":{"amount":205317,"percentage":7.5},"period":"שנה","order_period":2},{"section":"40-49","male":{"amount":114180,"percentage":5.3},"female":{"amount":170257,"percentage":7.9},"period":"3 חודשים","order_period":4},{"section":"40-49","male":{"amount":129247,"percentage":5.2},"female":{"amount":189708,"percentage":7.6},"period":"6 חודשים","order_period":3},{"section":"40-49","male":{"amount":182076,"percentage":5.2},"female":{"amount":253520,"percentage":7.3},"period":"מתחילת קורונה","order_period":1},{"section":"50-59","female":{"amount":75642,"percentage":5.1},"male":{"amount":50847,"percentage":3.4},"period":"חודש אחרון","order_period":5},{"section":"50-59","female":{"amount":117033,"percentage":4.7},"male":{"amount":81754,"percentage":3.3},"period":"6 חודשים","order_period":3},{"section":"50-59","female":{"amount":107412,"percentage":5},"male":{"amount":74460,"percentage":3.5},"period":"3 חודשים","order_period":4},{"section":"50-59","female":{"amount":162212,"percentage":4.7},"male":{"amount":120535,"percentage":3.5},"period":"מתחילת קורונה","order_period":1},{"section":"50-59","female":{"amount":127169,"percentage":4.6},"male":{"amount":89873,"percentage":3.3},"period":"שנה","order_period":2},{"section":"60-69","male":{"amount":59792,"percentage":2.2},"female":{"amount":80827,"percentage":2.9},"period":"שנה","order_period":2},{"section":"60-69","male":{"amount":50038,"percentage":2.3},"female":{"amount":68793,"percentage":3.2},"period":"3 חודשים","order_period":4},{"section":"60-69","male":{"amount":32502,"percentage":2.2},"female":{"amount":47135,"percentage":3.2},"period":"חודש אחרון","order_period":5},{"section":"60-69","male":{"amount":53997,"percentage":2.2},"female":{"amount":73875,"percentage":3},"period":"6 חודשים","order_period":3},{"section":"60-69","male":{"amount":80911,"percentage":2.3},"female":{"amount":102451,"percentage":2.9},"period":"מתחילת קורונה","order_period":1},{"section":"70-79","female":{"amount":50343,"percentage":1.4},"male":{"amount":42774,"percentage":1.2},"period":"מתחילת קורונה","order_period":1},{"section":"70-79","female":{"amount":39455,"percentage":1.4},"male":{"amount":32233,"percentage":1.2},"period":"שנה","order_period":2},{"section":"70-79","female":{"amount":35542,"percentage":1.4},"male":{"amount":28869,"percentage":1.2},"period":"6 חודשים","order_period":3},{"section":"70-79","female":{"amount":22227,"percentage":1.5},"male":{"amount":17257,"percentage":1.2},"period":"חודש אחרון","order_period":5},{"section":"70-79","female":{"amount":33105,"percentage":1.5},"male":{"amount":26977,"percentage":1.3},"period":"3 חודשים","order_period":4},{"section":"80-89","male":{"amount":12083,"percentage":0.4},"female":{"amount":17064,"percentage":0.6},"period":"שנה","order_period":2},{"section":"80-89","male":{"amount":10587,"percentage":0.4},"female":{"amount":15112,"percentage":0.6},"period":"6 חודשים","order_period":3},{"section":"80-89","male":{"amount":9666,"percentage":0.4},"female":{"amount":13814,"percentage":0.6},"period":"3 חודשים","order_period":4},{"section":"80-89","male":{"amount":6574,"percentage":0.4},"female":{"amount":9759,"percentage":0.7},"period":"חודש אחרון","order_period":5},{"section":"80-89","male":{"amount":16816,"percentage":0.5},"female":{"amount":23628,"percentage":0.7},"period":"מתחילת קורונה","order_period":1},{"section":"90+","female":{"amount":5153,"percentage":0.2},"male":{"amount":2723,"percentage":0.1},"period":"שנה","order_period":2},{"section":"90+","female":{"amount":4148,"percentage":0.2},"male":{"amount":2180,"percentage":0.1},"period":"3 חודשים","order_period":4},{"section":"90+","female":{"amount":7728,"percentage":0.2},"male":{"amount":3937,"percentage":0.1},"period":"מתחילת קורונה","order_period":1},{"section":"90+","female":{"amount":2996,"percentage":0.2},"male":{"amount":1531,"percentage":0.1},"period":"חודש אחרון","order_period":5},{"section":"90+","female":{"amount":4545,"percentage":0.2},"male":{"amount":2385,"percentage":0.1},"period":"6 חודשים","order_period":3}]},{"id":"1","data":[{"section":"0-9","female":{"amount":1,"percentage":0.1},"male":{"amount":2,"percentage":0.1},"period":"חודש אחרון","order_period":5},{"section":"0-9","female":{"amount":3,"percentage":0.1},"male":{"amount":5,"percentage":0.1},"period":"שנה","order_period":2},{"section":"0-9","female":{"amount":1,"percentage":0},"male":{"amount":5,"percentage":0.2},"period":"6 חודשים","order_period":3},{"section":"0-9","female":{"amount":1,"percentage":0.1},"male":{"amount":4,"percentage":0.2},"period":"3 חודשים","order_period":4},{"section":"0-9","female":{"amount":4,"percentage":0},"male":{"amount":7,"percentage":0.1},"period":"מתחילת קורונה","order_period":1},{"section":"10-19","male":{"amount":2,"percentage":0},"female":{"amount":2,"percentage":0},"period":"שנה","order_period":2},{"section":"10-19","male":{"amount":1,"percentage":0.1},"female":{"amount":1,"percentage":0.1},"period":"3 חודשים","order_period":4},{"section":"10-19","male":{"amount":1,"percentage":0.1},"female":{"amount":1,"percentage":0.1},"period":"חודש אחרון","order_period":5},{"section":"10-19","male":{"amount":4,"percentage":0},"female":{"amount":5,"percentage":0.1},"period":"מתחילת קורונה","order_period":1},{"section":"10-19","male":{"amount":2,"percentage":0.1},"female":{"amount":2,"percentage":0.1},"period":"6 חודשים","order_period":3},{"section":"20-29","female":{"amount":5,"percentage":0.2},"male":{"amount":5,"percentage":0.2},"period":"6 חודשים","order_period":3},{"section":"20-29","female":{"amount":3,"percentage":0.2},"male":{"amount":1,"percentage":0.1},"period":"חודש אחרון","order_period":5},{"section":"20-29","female":{"amount":10,"percentage":0.2},"male":{"amount":12,"percentage":0.3},"period":"שנה","order_period":2},{"section":"20-29","female":{"amount":3,"percentage":0.2},"male":{"amount":2,"percentage":0.1},"period":"3 חודשים","order_period":4},{"section":"20-29","female":{"amount":19,"percentage":0.2},"male":{"amount":24,"percentage":0.2},"period":"מתחילת קורונה","order_period":1},{"section":"30-39","male":{"amount":7,"percentage":0.4},"female":{"amount":3,"percentage":0.2},"period":"3 חודשים","order_period":4},{"section":"30-39","male":{"amount":30,"percentage":0.7},"female":{"amount":19,"percentage":0.4},"period":"שנה","order_period":2},{"section":"30-39","male":{"amount":17,"percentage":0.6},"female":{"amount":12,"percentage":0.4},"period":"6 חודשים","order_period":3},{"section":"30-39","male":{"amount":4,"percentage":0.3},"female":{"amount":3,"percentage":0.2},"period":"חודש אחרון","order_period":5},{"section":"30-39","male":{"amount":49,"percentage":0.5},"female":{"amount":34,"percentage":0.3},"period":"מתחילת קורונה","order_period":1},{"section":"40-49","male":{"amount":9,"percentage":0.6},"female":{"amount":6,"percentage":0.4},"period":"חודש אחרון","order_period":5},{"section":"40-49","male":{"amount":70,"percentage":1.6},"female":{"amount":39,"percentage":0.9},"period":"שנה","order_period":2},{"section":"40-49","male":{"amount":15,"percentage":0.9},"female":{"amount":9,"percentage":0.6},"period":"3 חודשים","order_period":4},{"section":"40-49","male":{"amount":44,"percentage":1.5},"female":{"amount":18,"percentage":0.6},"period":"6 חודשים","order_period":3},{"section":"40-49","male":{"amount":114,"percentage":1.2},"female":{"amount":73,"percentage":0.7},"period":"מתחילת קורונה","order_period":1},{"section":"50-59","female":{"amount":21,"percentage":1.5},"male":{"amount":30,"percentage":2.1},"period":"חודש אחרון","order_period":5},{"section":"50-59","female":{"amount":55,"percentage":1.9},"male":{"amount":98,"percentage":3.3},"period":"6 חודשים","order_period":3},{"section":"50-59","female":{"amount":27,"percentage":1.7},"male":{"amount":40,"percentage":2.5},"period":"3 חודשים","order_period":4},{"section":"50-59","female":{"amount":185,"percentage":1.9},"male":{"amount":356,"percentage":3.6},"period":"מתחילת קורונה","order_period":1},{"section":"50-59","female":{"amount":96,"percentage":2.2},"male":{"amount":164,"percentage":3.8},"period":"שנה","order_period":2},{"section":"60-69","male":{"amount":377,"percentage":8.7},"female":{"amount":266,"percentage":6.2},"period":"שנה","order_period":2},{"section":"60-69","male":{"amount":101,"percentage":6.2},"female":{"amount":61,"percentage":3.8},"period":"3 חודשים","order_period":4},{"section":"60-69","male":{"amount":80,"percentage":5.7},"female":{"amount":47,"percentage":3.4},"period":"חודש אחרון","order_period":5},{"section":"60-69","male":{"amount":237,"percentage":8.1},"female":{"amount":176,"percentage":6},"period":"6 חודשים","order_period":3},{"section":"60-69","male":{"amount":916,"percentage":9.4},"female":{"amount":505,"percentage":5.2},"period":"מתחילת קורונה","order_period":1},{"section":"70-79","female":{"amount":935,"percentage":9.5},"male":{"amount":1498,"percentage":15.3},"period":"מתחילת קורונה","order_period":1},{"section":"70-79","female":{"amount":462,"percentage":10.7},"male":{"amount":597,"percentage":13.8},"period":"שנה","order_period":2},{"section":"70-79","female":{"amount":300,"percentage":10.2},"male":{"amount":400,"percentage":13.6},"period":"6 חודשים","order_period":3},{"section":"70-79","female":{"amount":124,"percentage":8.9},"male":{"amount":184,"percentage":13.2},"period":"חודש אחרון","order_period":5},{"section":"70-79","female":{"amount":152,"percentage":9.4},"male":{"amount":209,"percentage":12.9},"period":"3 חודשים","order_period":4},{"section":"80-89","male":{"amount":727,"percentage":16.9},"female":{"amount":701,"percentage":16.3},"period":"שנה","order_period":2},{"section":"80-89","male":{"amount":513,"percentage":17.4},"female":{"amount":495,"percentage":16.8},"period":"6 חודשים","order_period":3},{"section":"80-89","male":{"amount":304,"percentage":18.8},"female":{"amount":303,"percentage":18.7},"period":"3 חודשים","order_period":4},{"section":"80-89","male":{"amount":277,"percentage":19.8},"female":{"amount":265,"percentage":19},"period":"חודש אחרון","order_period":5},{"section":"80-89","male":{"amount":1708,"percentage":17.4},"female":{"amount":1567,"percentage":16},"period":"מתחילת קורונה","order_period":1},{"section":"90+","female":{"amount":424,"percentage":9.8},"male":{"amount":307,"percentage":7.1},"period":"שנה","order_period":2},{"section":"90+","female":{"amount":208,"percentage":12.9},"male":{"amount":167,"percentage":10.3},"period":"3 חודשים","order_period":4},{"section":"90+","female":{"amount":1035,"percentage":10.6},"male":{"amount":758,"percentage":7.7},"period":"מתחילת קורונה","order_period":1},{"section":"90+","female":{"amount":181,"percentage":13},"male":{"amount":156,"percentage":11.2},"period":"חודש אחרון","order_period":5},{"section":"90+","female":{"amount":324,"percentage":11},"male":{"amount":233,"percentage":7.9},"period":"6 חודשים","order_period":3}]},{"id":"2","data":[{"section":"0-9","female":{"amount":6,"percentage":0.7},"male":{"amount":11,"percentage":1.3},"period":"חודש אחרון","order_period":5},{"section":"0-9","female":{"amount":10,"percentage":0.4},"male":{"amount":19,"percentage":0.7},"period":"שנה","order_period":2},{"section":"0-9","female":{"amount":6,"percentage":0.3},"male":{"amount":17,"percentage":1},"period":"6 חודשים","order_period":3},{"section":"0-9","female":{"amount":6,"percentage":0.6},"male":{"amount":12,"percentage":1.2},"period":"3 חודשים","order_period":4},{"section":"0-9","female":{"amount":13,"percentage":0.2},"male":{"amount":26,"percentage":0.5},"period":"מתחילת קורונה","order_period":1},{"section":"10-19","male":{"amount":14,"percentage":0.5},"female":{"amount":15,"percentage":0.6},"period":"שנה","order_period":2},{"section":"10-19","male":{"amount":8,"percentage":0.8},"female":{"amount":7,"percentage":0.7},"period":"3 חודשים","order_period":4},{"section":"10-19","male":{"amount":8,"percentage":0.9},"female":{"amount":6,"percentage":0.7},"period":"חודש אחרון","order_period":5},{"section":"10-19","male":{"amount":23,"percentage":0.4},"female":{"amount":19,"percentage":0.3},"period":"מתחילת קורונה","order_period":1},{"section":"10-19","male":{"amount":13,"percentage":0.7},"female":{"amount":12,"percentage":0.7},"period":"6 חודשים","order_period":3},{"section":"20-29","female":{"amount":16,"percentage":0.9},"male":{"amount":20,"percentage":1.1},"period":"6 חודשים","order_period":3},{"section":"20-29","female":{"amount":9,"percentage":1},"male":{"amount":8,"percentage":0.9},"period":"חודש אחרון","order_period":5},{"section":"20-29","female":{"amount":26,"percentage":1},"male":{"amount":36,"percentage":1.3},"period":"שנה","order_period":2},{"section":"20-29","female":{"amount":12,"percentage":1.2},"male":{"amount":10,"percentage":1},"period":"3 חודשים","order_period":4},{"section":"20-29","female":{"amount":55,"percentage":1},"male":{"amount":50,"percentage":0.9},"period":"מתחילת קורונה","order_period":1},{"section":"30-39","male":{"amount":15,"percentage":1.5},"female":{"amount":12,"percentage":1.2},"period":"3 חודשים","order_period":4},{"section":"30-39","male":{"amount":50,"percentage":1.8},"female":{"amount":59,"percentage":2.2},"period":"שנה","order_period":2},{"section":"30-39","male":{"amount":30,"percentage":1.7},"female":{"amount":29,"percentage":1.6},"period":"6 חודשים","order_period":3},{"section":"30-39","male":{"amount":10,"percentage":1.2},"female":{"amount":7,"percentage":0.8},"period":"חודש אחרון","order_period":5},{"section":"30-39","male":{"amount":87,"percentage":1.5},"female":{"amount":89,"percentage":1.6},"period":"מתחילת קורונה","order_period":1},{"section":"40-49","male":{"amount":29,"percentage":3.4},"female":{"amount":15,"percentage":1.7},"period":"חודש אחרון","order_period":5},{"section":"40-49","male":{"amount":146,"percentage":5.4},"female":{"amount":80,"percentage":2.9},"period":"שנה","order_period":2},{"section":"40-49","male":{"amount":45,"percentage":4.4},"female":{"amount":21,"percentage":2.1},"period":"3 חודשים","order_period":4},{"section":"40-49","male":{"amount":86,"percentage":4.8},"female":{"amount":47,"percentage":2.6},"period":"6 חודשים","order_period":3},{"section":"40-49","male":{"amount":238,"percentage":4.2},"female":{"amount":139,"percentage":2.5},"period":"מתחילת קורונה","order_period":1},{"section":"50-59","female":{"amount":44,"percentage":5.1},"male":{"amount":68,"percentage":7.9},"period":"חודש אחרון","order_period":5},{"section":"50-59","female":{"amount":95,"percentage":5.3},"male":{"amount":159,"percentage":8.9},"period":"6 חודשים","order_period":3},{"section":"50-59","female":{"amount":54,"percentage":5.3},"male":{"amount":84,"percentage":8.2},"period":"3 חודשים","order_period":4},{"section":"50-59","female":{"amount":250,"percentage":4.4},"male":{"amount":513,"percentage":9.1},"period":"מתחילת קורונה","order_period":1},{"section":"50-59","female":{"amount":154,"percentage":5.7},"male":{"amount":255,"percentage":9.4},"period":"שנה","order_period":2},{"section":"60-69","male":{"amount":347,"percentage":12.8},"female":{"amount":249,"percentage":9.2},"period":"שנה","order_period":2},{"section":"60-69","male":{"amount":116,"percentage":11.4},"female":{"amount":71,"percentage":7},"period":"3 חודשים","order_period":4},{"section":"60-69","male":{"amount":95,"percentage":11},"female":{"amount":57,"percentage":6.6},"period":"חודש אחרון","order_period":5},{"section":"60-69","male":{"amount":218,"percentage":12.2},"female":{"amount":160,"percentage":9},"period":"6 חודשים","order_period":3},{"section":"60-69","male":{"amount":868,"percentage":15.4},"female":{"amount":456,"percentage":8.1},"period":"מתחילת קורונה","order_period":1},{"section":"70-79","female":{"amount":545,"percentage":9.7},"male":{"amount":966,"percentage":17.1},"period":"מתחילת קורונה","order_period":1},{"section":"70-79","female":{"amount":275,"percentage":10.1},"male":{"amount":375,"percentage":13.8},"period":"שנה","order_period":2},{"section":"70-79","female":{"amount":184,"percentage":10.3},"male":{"amount":249,"percentage":14},"period":"6 חודשים","order_period":3},{"section":"70-79","female":{"amount":85,"percentage":9.9},"male":{"amount":134,"percentage":15.6},"period":"חודש אחרון","order_period":5},{"section":"70-79","female":{"amount":98,"percentage":9.6},"male":{"amount":148,"percentage":14.5},"period":"3 חודשים","order_period":4},{"section":"80-89","male":{"amount":265,"percentage":9.7},"female":{"amount":231,"percentage":8.5},"period":"שנה","order_period":2},{"section":"80-89","male":{"amount":191,"percentage":10.7},"female":{"amount":160,"percentage":9},"period":"6 חודשים","order_period":3},{"section":"80-89","male":{"amount":126,"percentage":12.4},"female":{"amount":110,"percentage":10.8},"period":"3 חודשים","order_period":4},{"section":"80-89","male":{"amount":111,"percentage":12.9},"female":{"amount":99,"percentage":11.5},"period":"חודש אחרון","order_period":5},{"section":"80-89","male":{"amount":602,"percentage":10.7},"female":{"amount":455,"percentage":8.1},"period":"מתחילת קורונה","order_period":1},{"section":"90+","female":{"amount":61,"percentage":2.2},"male":{"amount":53,"percentage":1.9},"period":"שנה","order_period":2},{"section":"90+","female":{"amount":34,"percentage":3.3},"male":{"amount":30,"percentage":2.9},"period":"3 חודשים","order_period":4},{"section":"90+","female":{"amount":125,"percentage":2.2},"male":{"amount":126,"percentage":2.2},"period":"מתחילת קורונה","order_period":1},{"section":"90+","female":{"amount":30,"percentage":3.5},"male":{"amount":29,"percentage":3.4},"period":"חודש אחרון","order_period":5},{"section":"90+","female":{"amount":47,"percentage":2.6},"male":{"amount":41,"percentage":2.3},"period":"6 חודשים","order_period":3}]},{"id":"3","data":[{"section":"0-9","female":{"amount":22,"percentage":0.5},"male":{"amount":32,"percentage":0.8},"period":"חודש אחרון","order_period":5},{"section":"0-9","female":{"amount":52,"percentage":0.4},"male":{"amount":74,"percentage":0.6},"period":"שנה","order_period":2},{"section":"0-9","female":{"amount":40,"percentage":0.4},"male":{"amount":62,"percentage":0.7},"period":"6 חודשים","order_period":3},{"section":"0-9","female":{"amount":28,"percentage":0.6},"male":{"amount":39,"percentage":0.8},"period":"3 חודשים","order_period":4},{"section":"0-9","female":{"amount":63,"percentage":0.2},"male":{"amount":97,"percentage":0.4},"period":"מתחילת קורונה","order_period":1},{"section":"10-19","male":{"amount":43,"percentage":0.3},"female":{"amount":40,"percentage":0.3},"period":"שנה","order_period":2},{"section":"10-19","male":{"amount":20,"percentage":0.4},"female":{"amount":14,"percentage":0.3},"period":"3 חודשים","order_period":4},{"section":"10-19","male":{"amount":14,"percentage":0.3},"female":{"amount":8,"percentage":0.2},"period":"חודש אחרון","order_period":5},{"section":"10-19","male":{"amount":66,"percentage":0.2},"female":{"amount":63,"percentage":0.2},"period":"מתחילת קורונה","order_period":1},{"section":"10-19","male":{"amount":30,"percentage":0.3},"female":{"amount":26,"percentage":0.3},"period":"6 חודשים","order_period":3},{"section":"20-29","female":{"amount":84,"percentage":0.9},"male":{"amount":73,"percentage":0.8},"period":"6 חודשים","order_period":3},{"section":"20-29","female":{"amount":15,"percentage":0.4},"male":{"amount":22,"percentage":0.5},"period":"חודש אחרון","order_period":5},{"section":"20-29","female":{"amount":140,"percentage":1.1},"male":{"amount":134,"percentage":1},"period":"שנה","order_period":2},{"section":"20-29","female":{"amount":23,"percentage":0.5},"male":{"amount":29,"percentage":0.6},"period":"3 חודשים","order_period":4},{"section":"20-29","female":{"amount":246,"percentage":0.9},"male":{"amount":208,"percentage":0.8},"period":"מתחילת קורונה","order_period":1},{"section":"30-39","male":{"amount":44,"percentage":0.9},"female":{"amount":55,"percentage":1.1},"period":"3 חודשים","order_period":4},{"section":"30-39","male":{"amount":304,"percentage":2.3},"female":{"amount":314,"percentage":2.4},"period":"שנה","order_period":2},{"section":"30-39","male":{"amount":178,"percentage":2},"female":{"amount":175,"percentage":1.9},"period":"6 חודשים","order_period":3},{"section":"30-39","male":{"amount":32,"percentage":0.8},"female":{"amount":41,"percentage":1},"period":"חודש אחרון","order_period":5},{"section":"30-39","male":{"amount":568,"percentage":2.1},"female":{"amount":543,"percentage":2},"period":"מתחילת קורונה","order_period":1},{"section":"40-49","male":{"amount":83,"percentage":2},"female":{"amount":51,"percentage":1.2},"period":"חודש אחרון","order_period":5},{"section":"40-49","male":{"amount":636,"percentage":4.8},"female":{"amount":479,"percentage":3.6},"period":"שנה","order_period":2},{"section":"40-49","male":{"amount":112,"percentage":2.2},"female":{"amount":71,"percentage":1.4},"period":"3 חודשים","order_period":4},{"section":"40-49","male":{"amount":364,"percentage":4},"female":{"amount":278,"percentage":3.1},"period":"6 חודשים","order_period":3},{"section":"40-49","male":{"amount":1294,"percentage":4.8},"female":{"amount":892,"percentage":3.3},"period":"מתחילת קורונה","order_period":1},{"section":"50-59","female":{"amount":138,"percentage":3.3},"male":{"amount":207,"percentage":4.9},"period":"חודש אחרון","order_period":5},{"section":"50-59","female":{"amount":423,"percentage":4.7},"male":{"amount":593,"percentage":6.6},"period":"6 חודשים","order_period":3},{"section":"50-59","female":{"amount":168,"percentage":3.3},"male":{"amount":245,"percentage":4.9},"period":"3 חודשים","order_period":4},{"section":"50-59","female":{"amount":1478,"percentage":5.4},"male":{"amount":2145,"percentage":7.9},"period":"מתחילת קורונה","order_period":1},{"section":"50-59","female":{"amount":729,"percentage":5.5},"male":{"amount":929,"percentage":7},"period":"שנה","order_period":2},{"section":"60-69","male":{"amount":1317,"percentage":9.9},"female":{"amount":1026,"percentage":7.7},"period":"שנה","order_period":2},{"section":"60-69","male":{"amount":452,"percentage":9},"female":{"amount":326,"percentage":6.5},"period":"3 חודשים","order_period":4},{"section":"60-69","male":{"amount":375,"percentage":8.8},"female":{"amount":270,"percentage":6.4},"period":"חודש אחרון","order_period":5},{"section":"60-69","male":{"amount":880,"percentage":9.8},"female":{"amount":668,"percentage":7.4},"period":"6 חודשים","order_period":3},{"section":"60-69","male":{"amount":3098,"percentage":11.4},"female":{"amount":2091,"percentage":7.7},"period":"מתחילת קורונה","order_period":1},{"section":"70-79","female":{"amount":2572,"percentage":9.5},"male":{"amount":3521,"percentage":13},"period":"מתחילת קורונה","order_period":1},{"section":"70-79","female":{"amount":1289,"percentage":9.7},"male":{"amount":1568,"percentage":11.8},"period":"שנה","order_period":2},{"section":"70-79","female":{"amount":893,"percentage":9.9},"male":{"amount":1102,"percentage":12.2},"period":"6 חודשים","order_period":3},{"section":"70-79","female":{"amount":436,"percentage":10.3},"male":{"amount":594,"percentage":14},"period":"חודש אחרון","order_period":5},{"section":"70-79","female":{"amount":521,"percentage":10.3},"male":{"amount":695,"percentage":13.8},"period":"3 חודשים","order_period":4},{"section":"80-89","male":{"amount":1461,"percentage":11},"female":{"amount":1545,"percentage":11.6},"period":"שנה","order_period":2},{"section":"80-89","male":{"amount":1079,"percentage":12},"female":{"amount":1117,"percentage":12.4},"period":"6 חודשים","order_period":3},{"section":"80-89","male":{"amount":746,"percentage":14.8},"female":{"amount":764,"percentage":15.2},"period":"3 חודשים","order_period":4},{"section":"80-89","male":{"amount":648,"percentage":15.3},"female":{"amount":658,"percentage":15.5},"period":"חודש אחרון","order_period":5},{"section":"80-89","male":{"amount":2869,"percentage":10.6},"female":{"amount":2935,"percentage":10.8},"period":"מתחילת קורונה","order_period":1},{"section":"90+","female":{"amount":735,"percentage":5.5},"male":{"amount":480,"percentage":3.6},"period":"שנה","order_period":2},{"section":"90+","female":{"amount":397,"percentage":7.9},"male":{"amount":287,"percentage":5.7},"period":"3 חודשים","order_period":4},{"section":"90+","female":{"amount":1434,"percentage":5.3},"male":{"amount":955,"percentage":3.5},"period":"מתחילת קורונה","order_period":1},{"section":"90+","female":{"amount":344,"percentage":8.1},"male":{"amount":255,"percentage":6},"period":"חודש אחרון","order_period":5},{"section":"90+","female":{"amount":569,"percentage":6.3},"male":{"amount":378,"percentage":4.2},"period":"6 חודשים","order_period":3}]}]