[{"id":"0","data":[{"section":"0-9","period":"3 חודשים","order_period":0,"female":{"amount":9709,"percentage":12.0},"male":{"amount":10126,"percentage":12.5}},{"section":"10-19","period":"3 חודשים","order_period":0,"female":{"amount":9900,"percentage":12.2},"male":{"amount":8921,"percentage":11.0}},{"section":"20-29","period":"3 חודשים","order_period":0,"female":{"amount":7628,"percentage":9.4},"male":{"amount":5629,"percentage":6.9}},{"section":"30-39","period":"3 חודשים","order_period":0,"female":{"amount":6303,"percentage":7.8},"male":{"amount":4827,"percentage":5.9}},{"section":"40-49","period":"3 חודשים","order_period":0,"female":{"amount":4271,"percentage":5.3},"male":{"amount":3670,"percentage":4.5}},{"section":"50-59","period":"3 חודשים","order_period":0,"female":{"amount":2712,"percentage":3.3},"male":{"amount":2089,"percentage":2.6}},{"section":"60-69","period":"3 חודשים","order_period":0,"female":{"amount":1654,"percentage":2.0},"male":{"amount":1220,"percentage":1.5}},{"section":"70-79","period":"3 חודשים","order_period":0,"female":{"amount":817,"percentage":1.0},"male":{"amount":639,"percentage":0.8}},{"section":"80-89","period":"3 חודשים","order_period":0,"female":{"amount":500,"percentage":0.6},"male":{"amount":306,"percentage":0.4}},{"section":"90+","period":"3 חודשים","order_period":0,"female":{"amount":169,"percentage":0.2},"male":{"amount":86,"percentage":0.1}},{"section":"0-9","period":"6 חודשים","order_period":0,"female":{"amount":41800,"percentage":8.3},"male":{"amount":44393,"percentage":8.9}},{"section":"10-19","period":"6 חודשים","order_period":0,"female":{"amount":55941,"percentage":11.2},"male":{"amount":53844,"percentage":10.7}},{"section":"20-29","period":"6 חודשים","order_period":0,"female":{"amount":49201,"percentage":9.8},"male":{"amount":41679,"percentage":8.3}},{"section":"30-39","period":"6 חודשים","order_period":0,"female":{"amount":37328,"percentage":7.4},"male":{"amount":32863,"percentage":6.6}},{"section":"40-49","period":"6 חודשים","order_period":0,"female":{"amount":30637,"percentage":6.1},"male":{"amount":26529,"percentage":5.3}},{"section":"50-59","period":"6 חודשים","order_period":0,"female":{"amount":21227,"percentage":4.2},"male":{"amount":18973,"percentage":3.8}},{"section":"60-69","period":"6 חודשים","order_period":0,"female":{"amount":12981,"percentage":2.6},"male":{"amount":12173,"percentage":2.4}},{"section":"70-79","period":"6 חודשים","order_period":0,"female":{"amount":6661,"percentage":1.3},"male":{"amount":6056,"percentage":1.2}},{"section":"80-89","period":"6 חודשים","order_period":0,"female":{"amount":4122,"percentage":0.8},"male":{"amount":2793,"percentage":0.6}},{"section":"90+","period":"6 חודשים","order_period":0,"female":{"amount":1530,"percentage":0.3},"male":{"amount":788,"percentage":0.2}},{"section":"0-9","period":"חודש אחרון","order_period":0,"female":{"amount":89,"percentage":7.3},"male":{"amount":98,"percentage":8.1}},{"section":"10-19","period":"חודש אחרון","order_period":0,"female":{"amount":255,"percentage":21.0},"male":{"amount":208,"percentage":17.1}},{"section":"20-29","period":"חודש אחרון","order_period":0,"female":{"amount":46,"percentage":3.8},"male":{"amount":55,"percentage":4.5}},{"section":"30-39","period":"חודש אחרון","order_period":0,"female":{"amount":62,"percentage":5.1},"male":{"amount":57,"percentage":4.7}},{"section":"40-49","period":"חודש אחרון","order_period":0,"female":{"amount":53,"percentage":4.4},"male":{"amount":66,"percentage":5.4}},{"section":"50-59","period":"חודש אחרון","order_period":0,"female":{"amount":57,"percentage":4.7},"male":{"amount":35,"percentage":2.9}},{"section":"60-69","period":"חודש אחרון","order_period":0,"female":{"amount":25,"percentage":2.1},"male":{"amount":27,"percentage":2.2}},{"section":"70-79","period":"חודש אחרון","order_period":0,"female":{"amount":26,"percentage":2.1},"male":{"amount":15,"percentage":1.2}},{"section":"80-89","period":"חודש אחרון","order_period":0,"female":{"amount":16,"percentage":1.3},"male":{"amount":13,"percentage":1.1}},{"section":"90+","period":"חודש אחרון","order_period":0,"female":{"amount":10,"percentage":0.8},"male":{"amount":1,"percentage":0.1}},{"section":"0-9","period":"מתחילת קורונה","order_period":0,"female":{"amount":57974,"percentage":7.0},"male":{"amount":61264,"percentage":7.4}},{"section":"10-19","period":"מתחילת קורונה","order_period":0,"female":{"amount":84283,"percentage":10.2},"male":{"amount":92238,"percentage":11.1}},{"section":"20-29","period":"מתחילת קורונה","order_period":0,"female":{"amount":81184,"percentage":9.8},"male":{"amount":77143,"percentage":9.3}},{"section":"30-39","period":"מתחילת קורונה","order_period":0,"female":{"amount":60421,"percentage":7.3},"male":{"amount":55906,"percentage":6.7}},{"section":"40-49","period":"מתחילת קורונה","order_period":0,"female":{"amount":51856,"percentage":6.3},"male":{"amount":46462,"percentage":5.6}},{"section":"50-59","period":"מתחילת קורונה","order_period":0,"female":{"amount":37783,"percentage":4.6},"male":{"amount":34614,"percentage":4.2}},{"section":"60-69","period":"מתחילת קורונה","order_period":0,"female":{"amount":23432,"percentage":2.8},"male":{"amount":23722,"percentage":2.9}},{"section":"70-79","period":"מתחילת קורונה","order_period":0,"female":{"amount":11976,"percentage":1.4},"male":{"amount":11962,"percentage":1.4}},{"section":"80-89","period":"מתחילת קורונה","order_period":0,"female":{"amount":7297,"percentage":0.9},"male":{"amount":5300,"percentage":0.6}},{"section":"90+","period":"מתחילת קורונה","order_period":0,"female":{"amount":2943,"percentage":0.4},"male":{"amount":1409,"percentage":0.2}},{"section":"0-9","period":"שנה","order_period":0,"female":{"amount":57472,"percentage":7.1},"male":{"amount":60749,"percentage":7.5}},{"section":"10-19","period":"שנה","order_period":0,"female":{"amount":83188,"percentage":10.2},"male":{"amount":90964,"percentage":11.2}},{"section":"20-29","period":"שנה","order_period":0,"female":{"amount":79527,"percentage":9.8},"male":{"amount":74973,"percentage":9.2}},{"section":"30-39","period":"שנה","order_period":0,"female":{"amount":59486,"percentage":7.3},"male":{"amount":54644,"percentage":6.7}},{"section":"40-49","period":"שנה","order_period":0,"female":{"amount":50974,"percentage":6.3},"male":{"amount":45369,"percentage":5.6}},{"section":"50-59","period":"שנה","order_period":0,"female":{"amount":36886,"percentage":4.5},"male":{"amount":33585,"percentage":4.1}},{"section":"60-69","period":"שנה","order_period":0,"female":{"amount":22824,"percentage":2.8},"male":{"amount":22856,"percentage":2.8}},{"section":"70-79","period":"שנה","order_period":0,"female":{"amount":11597,"percentage":1.4},"male":{"amount":11472,"percentage":1.4}},{"section":"80-89","period":"שנה","order_period":0,"female":{"amount":7046,"percentage":0.9},"male":{"amount":5090,"percentage":0.6}},{"section":"90+","period":"שנה","order_period":0,"female":{"amount":2784,"percentage":0.3},"male":{"amount":1337,"percentage":0.2}}]},{"id":"1","data":[{"section":"0-9","period":"3 חודשים","order_period":0,"female":{"amount":2,"percentage":0.2},"male":{"amount":0,"percentage":0.0}},{"section":"10-19","period":"3 חודשים","order_period":0,"female":{"amount":0,"percentage":0.0},"male":{"amount":1,"percentage":0.1}},{"section":"20-29","period":"3 חודשים","order_period":0,"female":{"amount":1,"percentage":0.1},"male":{"amount":7,"percentage":0.9}},{"section":"30-39","period":"3 חודשים","order_period":0,"female":{"amount":4,"percentage":0.5},"male":{"amount":7,"percentage":0.9}},{"section":"40-49","period":"3 חודשים","order_period":0,"female":{"amount":20,"percentage":2.5},"male":{"amount":20,"percentage":2.5}},{"section":"50-59","period":"3 חודשים","order_period":0,"female":{"amount":29,"percentage":3.6},"male":{"amount":51,"percentage":6.3}},{"section":"60-69","period":"3 חודשים","order_period":0,"female":{"amount":56,"percentage":7.0},"male":{"amount":87,"percentage":10.8}},{"section":"70-79","period":"3 חודשים","order_period":0,"female":{"amount":110,"percentage":13.7},"male":{"amount":112,"percentage":13.9}},{"section":"80-89","period":"3 חודשים","order_period":0,"female":{"amount":110,"percentage":13.7},"male":{"amount":105,"percentage":13.0}},{"section":"90+","period":"3 חודשים","order_period":0,"female":{"amount":46,"percentage":5.7},"male":{"amount":37,"percentage":4.6}},{"section":"0-9","period":"6 חודשים","order_period":0,"female":{"amount":3,"percentage":0.1},"male":{"amount":1,"percentage":0.0}},{"section":"10-19","period":"6 חודשים","order_period":0,"female":{"amount":0,"percentage":0.0},"male":{"amount":3,"percentage":0.1}},{"section":"20-29","period":"6 חודשים","order_period":0,"female":{"amount":7,"percentage":0.2},"male":{"amount":18,"percentage":0.5}},{"section":"30-39","period":"6 חודשים","order_period":0,"female":{"amount":15,"percentage":0.4},"male":{"amount":17,"percentage":0.5}},{"section":"40-49","period":"6 חודשים","order_period":0,"female":{"amount":44,"percentage":1.2},"male":{"amount":48,"percentage":1.3}},{"section":"50-59","period":"6 חודשים","order_period":0,"female":{"amount":69,"percentage":1.9},"male":{"amount":153,"percentage":4.3}},{"section":"60-69","period":"6 חודשים","order_period":0,"female":{"amount":190,"percentage":5.3},"male":{"amount":378,"percentage":10.6}},{"section":"70-79","period":"6 חודשים","order_period":0,"female":{"amount":367,"percentage":10.3},"male":{"amount":555,"percentage":15.6}},{"section":"80-89","period":"6 חודשים","order_period":0,"female":{"amount":551,"percentage":15.4},"male":{"amount":587,"percentage":16.4}},{"section":"90+","period":"6 חודשים","order_period":0,"female":{"amount":307,"percentage":8.6},"male":{"amount":256,"percentage":7.2}},{"section":"0-9","period":"חודש אחרון","order_period":0,"female":{"amount":0,"percentage":0.0},"male":{"amount":0,"percentage":0.0}},{"section":"10-19","period":"חודש אחרון","order_period":0,"female":{"amount":0,"percentage":0.0},"male":{"amount":0,"percentage":0.0}},{"section":"20-29","period":"חודש אחרון","order_period":0,"female":{"amount":0,"percentage":0.0},"male":{"amount":0,"percentage":0.0}},{"section":"30-39","period":"חודש אחרון","order_period":0,"female":{"amount":0,"percentage":0.0},"male":{"amount":0,"percentage":0.0}},{"section":"40-49","period":"חודש אחרון","order_period":0,"female":{"amount":0,"percentage":0.0},"male":{"amount":3,"percentage":6.7}},{"section":"50-59","period":"חודש אחרון","order_period":0,"female":{"amount":3,"percentage":6.7},"male":{"amount":10,"percentage":22.2}},{"section":"60-69","period":"חודש אחרון","order_period":0,"female":{"amount":1,"percentage":2.2},"male":{"amount":2,"percentage":4.4}},{"section":"70-79","period":"חודש אחרון","order_period":0,"female":{"amount":5,"percentage":11.1},"male":{"amount":4,"percentage":8.9}},{"section":"80-89","period":"חודש אחרון","order_period":0,"female":{"amount":4,"percentage":8.9},"male":{"amount":7,"percentage":15.6}},{"section":"90+","period":"חודש אחרון","order_period":0,"female":{"amount":5,"percentage":11.1},"male":{"amount":1,"percentage":2.2}},{"section":"0-9","period":"מתחילת קורונה","order_period":0,"female":{"amount":3,"percentage":0.0},"male":{"amount":2,"percentage":0.0}},{"section":"10-19","period":"מתחילת קורונה","order_period":0,"female":{"amount":3,"percentage":0.0},"male":{"amount":4,"percentage":0.1}},{"section":"20-29","period":"מתחילת קורונה","order_period":0,"female":{"amount":12,"percentage":0.2},"male":{"amount":19,"percentage":0.3}},{"section":"30-39","period":"מתחילת קורונה","order_period":0,"female":{"amount":21,"percentage":0.3},"male":{"amount":28,"percentage":0.4}},{"section":"40-49","period":"מתחילת קורונה","order_period":0,"female":{"amount":56,"percentage":0.9},"male":{"amount":69,"percentage":1.1}},{"section":"50-59","period":"מתחילת קורונה","order_period":0,"female":{"amount":121,"percentage":1.9},"male":{"amount":250,"percentage":3.9}},{"section":"60-69","period":"מתחילת קורונה","order_period":0,"female":{"amount":299,"percentage":4.7},"male":{"amount":640,"percentage":10.0}},{"section":"70-79","period":"מתחילת קורונה","order_period":0,"female":{"amount":597,"percentage":9.3},"male":{"amount":1027,"percentage":16.0}},{"section":"80-89","period":"מתחילת קורונה","order_period":0,"female":{"amount":989,"percentage":15.4},"male":{"amount":1114,"percentage":17.4}},{"section":"90+","period":"מתחילת קורונה","order_period":0,"female":{"amount":662,"percentage":10.3},"male":{"amount":490,"percentage":7.6}},{"section":"0-9","period":"שנה","order_period":0,"female":{"amount":3,"percentage":0.0},"male":{"amount":2,"percentage":0.0}},{"section":"10-19","period":"שנה","order_period":0,"female":{"amount":3,"percentage":0.0},"male":{"amount":3,"percentage":0.0}},{"section":"20-29","period":"שנה","order_period":0,"female":{"amount":11,"percentage":0.2},"male":{"amount":19,"percentage":0.3}},{"section":"30-39","period":"שנה","order_period":0,"female":{"amount":21,"percentage":0.3},"male":{"amount":26,"percentage":0.4}},{"section":"40-49","period":"שנה","order_period":0,"female":{"amount":54,"percentage":0.9},"male":{"amount":66,"percentage":1.1}},{"section":"50-59","period":"שנה","order_period":0,"female":{"amount":116,"percentage":1.9},"male":{"amount":246,"percentage":4.0}},{"section":"60-69","period":"שנה","order_period":0,"female":{"amount":290,"percentage":4.7},"male":{"amount":623,"percentage":10.2}},{"section":"70-79","period":"שנה","order_period":0,"female":{"amount":576,"percentage":9.4},"male":{"amount":984,"percentage":16.1}},{"section":"80-89","period":"שנה","order_period":0,"female":{"amount":941,"percentage":15.4},"male":{"amount":1064,"percentage":17.4}},{"section":"90+","period":"שנה","order_period":0,"female":{"amount":614,"percentage":10.0},"male":{"amount":461,"percentage":7.5}}]},{"id":"2","data":[{"section":"0-9","period":"3 חודשים","order_period":0,"female":{"amount":4,"percentage":0.6},"male":{"amount":1,"percentage":0.1}},{"section":"10-19","period":"3 חודשים","order_period":0,"female":{"amount":3,"percentage":0.4},"male":{"amount":2,"percentage":0.3}},{"section":"20-29","period":"3 חודשים","order_period":0,"female":{"amount":8,"percentage":1.2},"male":{"amount":13,"percentage":1.9}},{"section":"30-39","period":"3 חודשים","order_period":0,"female":{"amount":27,"percentage":4.0},"male":{"amount":16,"percentage":2.4}},{"section":"40-49","period":"3 חודשים","order_period":0,"female":{"amount":23,"percentage":3.4},"male":{"amount":54,"percentage":7.9}},{"section":"50-59","period":"3 חודשים","order_period":0,"female":{"amount":48,"percentage":7.1},"male":{"amount":83,"percentage":12.2}},{"section":"60-69","period":"3 חודשים","order_period":0,"female":{"amount":62,"percentage":9.1},"male":{"amount":90,"percentage":13.2}},{"section":"70-79","period":"3 חודשים","order_period":0,"female":{"amount":68,"percentage":10.0},"male":{"amount":82,"percentage":12.1}},{"section":"80-89","period":"3 חודשים","order_period":0,"female":{"amount":33,"percentage":4.9},"male":{"amount":47,"percentage":6.9}},{"section":"90+","period":"3 חודשים","order_period":0,"female":{"amount":10,"percentage":1.5},"male":{"amount":6,"percentage":0.9}},{"section":"0-9","period":"6 חודשים","order_period":0,"female":{"amount":6,"percentage":0.3},"male":{"amount":3,"percentage":0.1}},{"section":"10-19","period":"6 חודשים","order_period":0,"female":{"amount":3,"percentage":0.1},"male":{"amount":6,"percentage":0.3}},{"section":"20-29","period":"6 חודשים","order_period":0,"female":{"amount":20,"percentage":1.0},"male":{"amount":23,"percentage":1.1}},{"section":"30-39","period":"6 חודשים","order_period":0,"female":{"amount":47,"percentage":2.3},"male":{"amount":32,"percentage":1.6}},{"section":"40-49","period":"6 חודשים","order_period":0,"female":{"amount":54,"percentage":2.6},"male":{"amount":102,"percentage":5.0}},{"section":"50-59","period":"6 חודשים","order_period":0,"female":{"amount":89,"percentage":4.3},"male":{"amount":208,"percentage":10.1}},{"section":"60-69","period":"6 חודשים","order_period":0,"female":{"amount":170,"percentage":8.3},"male":{"amount":330,"percentage":16.1}},{"section":"70-79","period":"6 חודשים","order_period":0,"female":{"amount":200,"percentage":9.8},"male":{"amount":344,"percentage":16.8}},{"section":"80-89","period":"6 חודשים","order_period":0,"female":{"amount":155,"percentage":7.6},"male":{"amount":189,"percentage":9.2}},{"section":"90+","period":"6 חודשים","order_period":0,"female":{"amount":36,"percentage":1.8},"male":{"amount":33,"percentage":1.6}},{"section":"0-9","period":"חודש אחרון","order_period":0,"female":{"amount":0,"percentage":0.0},"male":{"amount":0,"percentage":0.0}},{"section":"10-19","period":"חודש אחרון","order_period":0,"female":{"amount":1,"percentage":1.0},"male":{"amount":0,"percentage":0.0}},{"section":"20-29","period":"חודש אחרון","order_period":0,"female":{"amount":0,"percentage":0.0},"male":{"amount":0,"percentage":0.0}},{"section":"30-39","period":"חודש אחרון","order_period":0,"female":{"amount":5,"percentage":4.8},"male":{"amount":2,"percentage":1.9}},{"section":"40-49","period":"חודש אחרון","order_period":0,"female":{"amount":1,"percentage":1.0},"male":{"amount":16,"percentage":15.4}},{"section":"50-59","period":"חודש אחרון","order_period":0,"female":{"amount":13,"percentage":12.5},"male":{"amount":22,"percentage":21.2}},{"section":"60-69","period":"חודש אחרון","order_period":0,"female":{"amount":9,"percentage":8.7},"male":{"amount":12,"percentage":11.5}},{"section":"70-79","period":"חודש אחרון","order_period":0,"female":{"amount":7,"percentage":6.7},"male":{"amount":6,"percentage":5.8}},{"section":"80-89","period":"חודש אחרון","order_period":0,"female":{"amount":4,"percentage":3.8},"male":{"amount":5,"percentage":4.8}},{"section":"90+","period":"חודש אחרון","order_period":0,"female":{"amount":1,"percentage":1.0},"male":{"amount":0,"percentage":0.0}},{"section":"0-9","period":"מתחילת קורונה","order_period":0,"female":{"amount":9,"percentage":0.2},"male":{"amount":7,"percentage":0.2}},{"section":"10-19","period":"מתחילת קורונה","order_period":0,"female":{"amount":8,"percentage":0.2},"male":{"amount":12,"percentage":0.3}},{"section":"20-29","period":"מתחילת קורונה","order_period":0,"female":{"amount":36,"percentage":1.0},"male":{"amount":31,"percentage":0.8}},{"section":"30-39","period":"מתחילת קורונה","order_period":0,"female":{"amount":66,"percentage":1.8},"male":{"amount":58,"percentage":1.6}},{"section":"40-49","period":"מתחילת קורונה","order_period":0,"female":{"amount":83,"percentage":2.2},"male":{"amount":161,"percentage":4.4}},{"section":"50-59","period":"מתחילת קורונה","order_period":0,"female":{"amount":146,"percentage":3.9},"male":{"amount":353,"percentage":9.5}},{"section":"60-69","period":"מתחילת קורונה","order_period":0,"female":{"amount":284,"percentage":7.7},"male":{"amount":627,"percentage":17.0}},{"section":"70-79","period":"מתחילת קורונה","order_period":0,"female":{"amount":338,"percentage":9.1},"male":{"amount":674,"percentage":18.2}},{"section":"80-89","period":"מתחילת קורונה","order_period":0,"female":{"amount":267,"percentage":7.2},"male":{"amount":389,"percentage":10.5}},{"section":"90+","period":"מתחילת קורונה","order_period":0,"female":{"amount":72,"percentage":1.9},"male":{"amount":78,"percentage":2.1}},{"section":"0-9","period":"שנה","order_period":0,"female":{"amount":9,"percentage":0.3},"male":{"amount":5,"percentage":0.1}},{"section":"10-19","period":"שנה","order_period":0,"female":{"amount":7,"percentage":0.2},"male":{"amount":10,"percentage":0.3}},{"section":"20-29","period":"שנה","order_period":0,"female":{"amount":33,"percentage":1.0},"male":{"amount":29,"percentage":0.8}},{"section":"30-39","period":"שנה","order_period":0,"female":{"amount":63,"percentage":1.8},"male":{"amount":47,"percentage":1.4}},{"section":"40-49","period":"שנה","order_period":0,"female":{"amount":78,"percentage":2.3},"male":{"amount":150,"percentage":4.4}},{"section":"50-59","period":"שנה","order_period":0,"female":{"amount":141,"percentage":4.1},"male":{"amount":326,"percentage":9.5}},{"section":"60-69","period":"שנה","order_period":0,"female":{"amount":273,"percentage":8.0},"male":{"amount":586,"percentage":17.1}},{"section":"70-79","period":"שנה","order_period":0,"female":{"amount":319,"percentage":9.3},"male":{"amount":622,"percentage":18.1}},{"section":"80-89","period":"שנה","order_period":0,"female":{"amount":248,"percentage":7.2},"male":{"amount":354,"percentage":10.3}},{"section":"90+","period":"שנה","order_period":0,"female":{"amount":63,"percentage":1.8},"male":{"amount":67,"percentage":2.0}}]},{"id":"3","data":[{"section":"0-9","period":"3 חודשים","order_period":0,"female":{"amount":9,"percentage":0.4},"male":{"amount":4,"percentage":0.2}},{"section":"10-19","period":"3 חודשים","order_period":0,"female":{"amount":10,"percentage":0.4},"male":{"amount":6,"percentage":0.2}},{"section":"20-29","period":"3 חודשים","order_period":0,"female":{"amount":44,"percentage":1.7},"male":{"amount":52,"percentage":2.0}},{"section":"30-39","period":"3 חודשים","order_period":0,"female":{"amount":98,"percentage":3.8},"male":{"amount":96,"percentage":3.8}},{"section":"40-49","period":"3 חודשים","order_period":0,"female":{"amount":140,"percentage":5.5},"male":{"amount":193,"percentage":7.6}},{"section":"50-59","period":"3 חודשים","order_period":0,"female":{"amount":199,"percentage":7.8},"male":{"amount":254,"percentage":10.0}},{"section":"60-69","period":"3 חודשים","order_period":0,"female":{"amount":239,"percentage":9.4},"male":{"amount":244,"percentage":9.6}},{"section":"70-79","period":"3 חודשים","order_period":0,"female":{"amount":231,"percentage":9.1},"male":{"amount":230,"percentage":9.0}},{"section":"80-89","period":"3 חודשים","order_period":0,"female":{"amount":223,"percentage":8.7},"male":{"amount":167,"percentage":6.5}},{"section":"90+","period":"3 חודשים","order_period":0,"female":{"amount":69,"percentage":2.7},"male":{"amount":43,"percentage":1.7}},{"section":"0-9","period":"6 חודשים","order_period":0,"female":{"amount":14,"percentage":0.1},"male":{"amount":13,"percentage":0.1}},{"section":"10-19","period":"6 חודשים","order_period":0,"female":{"amount":27,"percentage":0.3},"male":{"amount":16,"percentage":0.2}},{"section":"20-29","period":"6 חודשים","order_period":0,"female":{"amount":101,"percentage":1.0},"male":{"amount":103,"percentage":1.1}},{"section":"30-39","period":"6 חודשים","order_period":0,"female":{"amount":232,"percentage":2.4},"male":{"amount":262,"percentage":2.7}},{"section":"40-49","period":"6 חודשים","order_period":0,"female":{"amount":381,"percentage":4.0},"male":{"amount":598,"percentage":6.2}},{"section":"50-59","period":"6 חודשים","order_period":0,"female":{"amount":589,"percentage":6.1},"male":{"amount":896,"percentage":9.3}},{"section":"60-69","period":"6 חודשים","order_period":0,"female":{"amount":752,"percentage":7.8},"male":{"amount":1085,"percentage":11.3}},{"section":"70-79","period":"6 חודשים","order_period":0,"female":{"amount":914,"percentage":9.5},"male":{"amount":1167,"percentage":12.1}},{"section":"80-89","period":"6 חודשים","order_period":0,"female":{"amount":927,"percentage":9.6},"male":{"amount":862,"percentage":9.0}},{"section":"90+","period":"6 חודשים","order_period":0,"female":{"amount":393,"percentage":4.1},"male":{"amount":299,"percentage":3.1}},{"section":"0-9","period":"חודש אחרון","order_period":0,"female":{"amount":1,"percentage":0.8},"male":{"amount":0,"percentage":0.0}},{"section":"10-19","period":"חודש אחרון","order_period":0,"female":{"amount":1,"percentage":0.8},"male":{"amount":0,"percentage":0.0}},{"section":"20-29","period":"חודש אחרון","order_period":0,"female":{"amount":1,"percentage":0.8},"male":{"amount":0,"percentage":0.0}},{"section":"30-39","period":"חודש אחרון","order_period":0,"female":{"amount":8,"percentage":6.7},"male":{"amount":1,"percentage":0.8}},{"section":"40-49","period":"חודש אחרון","order_period":0,"female":{"amount":2,"percentage":1.7},"male":{"amount":9,"percentage":7.6}},{"section":"50-59","period":"חודש אחרון","order_period":0,"female":{"amount":12,"percentage":10.1},"male":{"amount":5,"percentage":4.2}},{"section":"60-69","period":"חודש אחרון","order_period":0,"female":{"amount":16,"percentage":13.4},"male":{"amount":9,"percentage":7.6}},{"section":"70-79","period":"חודש אחרון","order_period":0,"female":{"amount":16,"percentage":13.4},"male":{"amount":8,"percentage":6.7}},{"section":"80-89","period":"חודש אחרון","order_period":0,"female":{"amount":8,"percentage":6.7},"male":{"amount":11,"percentage":9.2}},{"section":"90+","period":"חודש אחרון","order_period":0,"female":{"amount":10,"percentage":8.4},"male":{"amount":1,"percentage":0.8}},{"section":"0-9","period":"מתחילת קורונה","order_period":0,"female":{"amount":21,"percentage":0.1},"male":{"amount":23,"percentage":0.1}},{"section":"10-19","period":"מתחילת קורונה","order_period":0,"female":{"amount":44,"percentage":0.3},"male":{"amount":29,"percentage":0.2}},{"section":"20-29","period":"מתחילת קורונה","order_period":0,"female":{"amount":157,"percentage":0.9},"male":{"amount":144,"percentage":0.9}},{"section":"30-39","period":"מתחילת קורונה","order_period":0,"female":{"amount":343,"percentage":2.0},"male":{"amount":416,"percentage":2.5}},{"section":"40-49","period":"מתחילת קורונה","order_period":0,"female":{"amount":578,"percentage":3.5},"male":{"amount":941,"percentage":5.6}},{"section":"50-59","period":"מתחילת קורונה","order_period":0,"female":{"amount":977,"percentage":5.8},"male":{"amount":1521,"percentage":9.1}},{"section":"60-69","period":"מתחילת קורונה","order_period":0,"female":{"amount":1298,"percentage":7.8},"male":{"amount":2105,"percentage":12.6}},{"section":"70-79","period":"מתחילת קורונה","order_period":0,"female":{"amount":1533,"percentage":9.2},"male":{"amount":2203,"percentage":13.2}},{"section":"80-89","period":"מתחילת קורונה","order_period":0,"female":{"amount":1592,"percentage":9.5},"male":{"amount":1559,"percentage":9.3}},{"section":"90+","period":"מתחילת קורונה","order_period":0,"female":{"amount":749,"percentage":4.5},"male":{"amount":502,"percentage":3.0}},{"section":"0-9","period":"שנה","order_period":0,"female":{"amount":21,"percentage":0.1},"male":{"amount":21,"percentage":0.1}},{"section":"10-19","period":"שנה","order_period":0,"female":{"amount":43,"percentage":0.3},"male":{"amount":27,"percentage":0.2}},{"section":"20-29","period":"שנה","order_period":0,"female":{"amount":154,"percentage":0.9},"male":{"amount":142,"percentage":0.9}},{"section":"30-39","period":"שנה","order_period":0,"female":{"amount":339,"percentage":2.1},"male":{"amount":405,"percentage":2.5}},{"section":"40-49","period":"שנה","order_period":0,"female":{"amount":570,"percentage":3.5},"male":{"amount":926,"percentage":5.7}},{"section":"50-59","period":"שנה","order_period":0,"female":{"amount":970,"percentage":6.0},"male":{"amount":1476,"percentage":9.1}},{"section":"60-69","period":"שנה","order_period":0,"female":{"amount":1279,"percentage":7.9},"male":{"amount":2049,"percentage":12.6}},{"section":"70-79","period":"שנה","order_period":0,"female":{"amount":1498,"percentage":9.2},"male":{"amount":2125,"percentage":13.0}},{"section":"80-89","period":"שנה","order_period":0,"female":{"amount":1540,"percentage":9.5},"male":{"amount":1506,"percentage":9.2}},{"section":"90+","period":"שנה","order_period":0,"female":{"amount":716,"percentage":4.4},"male":{"amount":477,"percentage":2.9}}]}]