[{"id":"0","data":[{"section":"0-9","period":"3 חודשים","order_period":0,"female":{"amount":6929,"percentage":10.5},"male":{"amount":6768,"percentage":10.2}},{"section":"10-19","period":"3 חודשים","order_period":0,"female":{"amount":6600,"percentage":10.0},"male":{"amount":5967,"percentage":9.0}},{"section":"20-29","period":"3 חודשים","order_period":0,"female":{"amount":4237,"percentage":6.4},"male":{"amount":3573,"percentage":5.4}},{"section":"30-39","period":"3 חודשים","order_period":0,"female":{"amount":4838,"percentage":7.3},"male":{"amount":3765,"percentage":5.7}},{"section":"40-49","period":"3 חודשים","order_period":0,"female":{"amount":4591,"percentage":6.9},"male":{"amount":3778,"percentage":5.7}},{"section":"50-59","period":"3 חודשים","order_period":0,"female":{"amount":3045,"percentage":4.6},"male":{"amount":2527,"percentage":3.8}},{"section":"60-69","period":"3 חודשים","order_period":0,"female":{"amount":2596,"percentage":3.9},"male":{"amount":2273,"percentage":3.4}},{"section":"70-79","period":"3 חודשים","order_period":0,"female":{"amount":1607,"percentage":2.4},"male":{"amount":1457,"percentage":2.2}},{"section":"80-89","period":"3 חודשים","order_period":0,"female":{"amount":715,"percentage":1.1},"male":{"amount":610,"percentage":0.9}},{"section":"90+","period":"3 חודשים","order_period":0,"female":{"amount":237,"percentage":0.4},"male":{"amount":106,"percentage":0.2}},{"section":"0-9","period":"6 חודשים","order_period":0,"female":{"amount":21992,"percentage":11.1},"male":{"amount":22311,"percentage":11.3}},{"section":"10-19","period":"6 חודשים","order_period":0,"female":{"amount":21951,"percentage":11.1},"male":{"amount":19791,"percentage":10.0}},{"section":"20-29","period":"6 חודשים","order_period":0,"female":{"amount":17589,"percentage":8.9},"male":{"amount":13632,"percentage":6.9}},{"section":"30-39","period":"6 חודשים","order_period":0,"female":{"amount":15068,"percentage":7.6},"male":{"amount":12101,"percentage":6.1}},{"section":"40-49","period":"6 חודשים","order_period":0,"female":{"amount":11715,"percentage":5.9},"male":{"amount":9772,"percentage":4.9}},{"section":"50-59","period":"6 חודשים","order_period":0,"female":{"amount":7572,"percentage":3.8},"male":{"amount":6083,"percentage":3.1}},{"section":"60-69","period":"6 חודשים","order_period":0,"female":{"amount":5155,"percentage":2.6},"male":{"amount":4250,"percentage":2.2}},{"section":"70-79","period":"6 חודשים","order_period":0,"female":{"amount":2897,"percentage":1.5},"male":{"amount":2397,"percentage":1.2}},{"section":"80-89","period":"6 חודשים","order_period":0,"female":{"amount":1457,"percentage":0.7},"male":{"amount":1052,"percentage":0.5}},{"section":"90+","period":"6 חודשים","order_period":0,"female":{"amount":478,"percentage":0.2},"male":{"amount":227,"percentage":0.1}},{"section":"0-9","period":"חודש אחרון","order_period":0,"female":{"amount":6352,"percentage":10.6},"male":{"amount":6225,"percentage":10.4}},{"section":"10-19","period":"חודש אחרון","order_period":0,"female":{"amount":5560,"percentage":9.3},"male":{"amount":5093,"percentage":8.5}},{"section":"20-29","period":"חודש אחרון","order_period":0,"female":{"amount":3991,"percentage":6.7},"male":{"amount":3315,"percentage":5.5}},{"section":"30-39","period":"חודש אחרון","order_period":0,"female":{"amount":4519,"percentage":7.6},"male":{"amount":3496,"percentage":5.8}},{"section":"40-49","period":"חודש אחרון","order_period":0,"female":{"amount":4139,"percentage":6.9},"male":{"amount":3440,"percentage":5.8}},{"section":"50-59","period":"חודש אחרון","order_period":0,"female":{"amount":2768,"percentage":4.6},"male":{"amount":2273,"percentage":3.8}},{"section":"60-69","period":"חודש אחרון","order_period":0,"female":{"amount":2337,"percentage":3.9},"male":{"amount":2033,"percentage":3.4}},{"section":"70-79","period":"חודש אחרון","order_period":0,"female":{"amount":1443,"percentage":2.4},"male":{"amount":1299,"percentage":2.2}},{"section":"80-89","period":"חודש אחרון","order_period":0,"female":{"amount":660,"percentage":1.1},"male":{"amount":556,"percentage":0.9}},{"section":"90+","period":"חודש אחרון","order_period":0,"female":{"amount":222,"percentage":0.4},"male":{"amount":102,"percentage":0.2}},{"section":"0-9","period":"מתחילת קורונה","order_period":0,"female":{"amount":68350,"percentage":7.6},"male":{"amount":70971,"percentage":7.9}},{"section":"10-19","period":"מתחילת קורונה","order_period":0,"female":{"amount":93249,"percentage":10.4},"male":{"amount":99698,"percentage":11.1}},{"section":"20-29","period":"מתחילת קורונה","order_period":0,"female":{"amount":85216,"percentage":9.5},"male":{"amount":77170,"percentage":8.6}},{"section":"30-39","period":"מתחילת קורונה","order_period":0,"female":{"amount":65217,"percentage":7.3},"male":{"amount":58415,"percentage":6.5}},{"section":"40-49","period":"מתחילת קורונה","order_period":0,"female":{"amount":56766,"percentage":6.3},"male":{"amount":49570,"percentage":5.5}},{"section":"50-59","period":"מתחילת קורונה","order_period":0,"female":{"amount":40420,"percentage":4.5},"male":{"amount":36395,"percentage":4.1}},{"section":"60-69","period":"מתחילת קורונה","order_period":0,"female":{"amount":25614,"percentage":2.9},"male":{"amount":25266,"percentage":2.8}},{"section":"70-79","period":"מתחילת קורונה","order_period":0,"female":{"amount":13289,"percentage":1.5},"male":{"amount":12785,"percentage":1.4}},{"section":"80-89","period":"מתחילת קורונה","order_period":0,"female":{"amount":7766,"percentage":0.9},"male":{"amount":5678,"percentage":0.6}},{"section":"90+","period":"מתחילת קורונה","order_period":0,"female":{"amount":2990,"percentage":0.3},"male":{"amount":1396,"percentage":0.2}},{"section":"0-9","period":"שנה","order_period":0,"female":{"amount":64175,"percentage":7.9},"male":{"amount":66620,"percentage":8.2}},{"section":"10-19","period":"שנה","order_period":0,"female":{"amount":86203,"percentage":10.6},"male":{"amount":91008,"percentage":11.2}},{"section":"20-29","period":"שנה","order_period":0,"female":{"amount":76786,"percentage":9.4},"male":{"amount":68324,"percentage":8.4}},{"section":"30-39","period":"שנה","order_period":0,"female":{"amount":59572,"percentage":7.3},"male":{"amount":52463,"percentage":6.4}},{"section":"40-49","period":"שנה","order_period":0,"female":{"amount":51492,"percentage":6.3},"male":{"amount":44527,"percentage":5.5}},{"section":"50-59","period":"שנה","order_period":0,"female":{"amount":36396,"percentage":4.5},"male":{"amount":32450,"percentage":4.0}},{"section":"60-69","period":"שנה","order_period":0,"female":{"amount":23076,"percentage":2.8},"male":{"amount":22512,"percentage":2.8}},{"section":"70-79","period":"שנה","order_period":0,"female":{"amount":12036,"percentage":1.5},"male":{"amount":11378,"percentage":1.4}},{"section":"80-89","period":"שנה","order_period":0,"female":{"amount":6962,"percentage":0.9},"male":{"amount":5083,"percentage":0.6}},{"section":"90+","period":"שנה","order_period":0,"female":{"amount":2610,"percentage":0.3},"male":{"amount":1235,"percentage":0.2}}]},{"id":"1","data":[{"section":"0-9","period":"3 חודשים","order_period":0,"female":{"amount":0,"percentage":0.0},"male":{"amount":0,"percentage":0.0}},{"section":"10-19","period":"3 חודשים","order_period":0,"female":{"amount":0,"percentage":0.0},"male":{"amount":0,"percentage":0.0}},{"section":"20-29","period":"3 חודשים","order_period":0,"female":{"amount":0,"percentage":0.0},"male":{"amount":0,"percentage":0.0}},{"section":"30-39","period":"3 חודשים","order_period":0,"female":{"amount":1,"percentage":0.6},"male":{"amount":3,"percentage":1.9}},{"section":"40-49","period":"3 חודשים","order_period":0,"female":{"amount":0,"percentage":0.0},"male":{"amount":2,"percentage":1.3}},{"section":"50-59","period":"3 חודשים","order_period":0,"female":{"amount":5,"percentage":3.2},"male":{"amount":6,"percentage":3.8}},{"section":"60-69","period":"3 חודשים","order_period":0,"female":{"amount":7,"percentage":4.5},"male":{"amount":9,"percentage":5.7}},{"section":"70-79","period":"3 חודשים","order_period":0,"female":{"amount":19,"percentage":12.1},"male":{"amount":24,"percentage":15.3}},{"section":"80-89","period":"3 חודשים","order_period":0,"female":{"amount":21,"percentage":13.4},"male":{"amount":30,"percentage":19.1}},{"section":"90+","period":"3 חודשים","order_period":0,"female":{"amount":16,"percentage":10.2},"male":{"amount":14,"percentage":8.9}},{"section":"0-9","period":"6 חודשים","order_period":0,"female":{"amount":2,"percentage":0.2},"male":{"amount":0,"percentage":0.0}},{"section":"10-19","period":"6 חודשים","order_period":0,"female":{"amount":0,"percentage":0.0},"male":{"amount":0,"percentage":0.0}},{"section":"20-29","period":"6 חודשים","order_period":0,"female":{"amount":4,"percentage":0.3},"male":{"amount":8,"percentage":0.6}},{"section":"30-39","period":"6 חודשים","order_period":0,"female":{"amount":9,"percentage":0.7},"male":{"amount":14,"percentage":1.1}},{"section":"40-49","period":"6 חודשים","order_period":0,"female":{"amount":23,"percentage":1.7},"male":{"amount":26,"percentage":2.0}},{"section":"50-59","period":"6 חודשים","order_period":0,"female":{"amount":41,"percentage":3.1},"male":{"amount":73,"percentage":5.5}},{"section":"60-69","period":"6 חודשים","order_period":0,"female":{"amount":86,"percentage":6.5},"male":{"amount":136,"percentage":10.2}},{"section":"70-79","period":"6 חודשים","order_period":0,"female":{"amount":168,"percentage":12.6},"male":{"amount":198,"percentage":14.9}},{"section":"80-89","period":"6 חודשים","order_period":0,"female":{"amount":196,"percentage":14.7},"male":{"amount":190,"percentage":14.3}},{"section":"90+","period":"6 חודשים","order_period":0,"female":{"amount":93,"percentage":7.0},"male":{"amount":62,"percentage":4.7}},{"section":"0-9","period":"חודש אחרון","order_period":0,"female":{"amount":0,"percentage":0.0},"male":{"amount":0,"percentage":0.0}},{"section":"10-19","period":"חודש אחרון","order_period":0,"female":{"amount":0,"percentage":0.0},"male":{"amount":0,"percentage":0.0}},{"section":"20-29","period":"חודש אחרון","order_period":0,"female":{"amount":0,"percentage":0.0},"male":{"amount":0,"percentage":0.0}},{"section":"30-39","period":"חודש אחרון","order_period":0,"female":{"amount":0,"percentage":0.0},"male":{"amount":2,"percentage":1.6}},{"section":"40-49","period":"חודש אחרון","order_period":0,"female":{"amount":0,"percentage":0.0},"male":{"amount":0,"percentage":0.0}},{"section":"50-59","period":"חודש אחרון","order_period":0,"female":{"amount":2,"percentage":1.6},"male":{"amount":2,"percentage":1.6}},{"section":"60-69","period":"חודש אחרון","order_period":0,"female":{"amount":4,"percentage":3.1},"male":{"amount":8,"percentage":6.2}},{"section":"70-79","period":"חודש אחרון","order_period":0,"female":{"amount":16,"percentage":12.4},"male":{"amount":23,"percentage":17.8}},{"section":"80-89","period":"חודש אחרון","order_period":0,"female":{"amount":18,"percentage":14.0},"male":{"amount":25,"percentage":19.4}},{"section":"90+","period":"חודש אחרון","order_period":0,"female":{"amount":15,"percentage":11.6},"male":{"amount":14,"percentage":10.9}},{"section":"0-9","period":"מתחילת קורונה","order_period":0,"female":{"amount":3,"percentage":0.0},"male":{"amount":2,"percentage":0.0}},{"section":"10-19","period":"מתחילת קורונה","order_period":0,"female":{"amount":3,"percentage":0.0},"male":{"amount":3,"percentage":0.0}},{"section":"20-29","period":"מתחילת קורונה","order_period":0,"female":{"amount":13,"percentage":0.2},"male":{"amount":19,"percentage":0.3}},{"section":"30-39","period":"מתחילת קורונה","order_period":0,"female":{"amount":22,"percentage":0.3},"male":{"amount":31,"percentage":0.5}},{"section":"40-49","period":"מתחילת קורונה","order_period":0,"female":{"amount":54,"percentage":0.8},"male":{"amount":70,"percentage":1.1}},{"section":"50-59","period":"מתחילת קורונה","order_period":0,"female":{"amount":126,"percentage":1.9},"male":{"amount":254,"percentage":3.9}},{"section":"60-69","period":"מתחילת קורונה","order_period":0,"female":{"amount":308,"percentage":4.7},"male":{"amount":649,"percentage":9.9}},{"section":"70-79","period":"מתחילת קורונה","order_period":0,"female":{"amount":616,"percentage":9.4},"male":{"amount":1051,"percentage":16.0}},{"section":"80-89","period":"מתחילת קורונה","order_period":0,"female":{"amount":1011,"percentage":15.4},"male":{"amount":1142,"percentage":17.4}},{"section":"90+","period":"מתחילת קורונה","order_period":0,"female":{"amount":679,"percentage":10.4},"male":{"amount":503,"percentage":7.7}},{"section":"0-9","period":"שנה","order_period":0,"female":{"amount":3,"percentage":0.1},"male":{"amount":2,"percentage":0.0}},{"section":"10-19","period":"שנה","order_period":0,"female":{"amount":1,"percentage":0.0},"male":{"amount":2,"percentage":0.0}},{"section":"20-29","period":"שנה","order_period":0,"female":{"amount":12,"percentage":0.2},"male":{"amount":18,"percentage":0.3}},{"section":"30-39","period":"שנה","order_period":0,"female":{"amount":22,"percentage":0.4},"male":{"amount":29,"percentage":0.5}},{"section":"40-49","period":"שנה","order_period":0,"female":{"amount":50,"percentage":0.8},"male":{"amount":63,"percentage":1.1}},{"section":"50-59","period":"שנה","order_period":0,"female":{"amount":116,"percentage":2.0},"male":{"amount":242,"percentage":4.1}},{"section":"60-69","period":"שנה","order_period":0,"female":{"amount":288,"percentage":4.9},"male":{"amount":609,"percentage":10.3}},{"section":"70-79","period":"שנה","order_period":0,"female":{"amount":569,"percentage":9.7},"male":{"amount":953,"percentage":16.2}},{"section":"80-89","period":"שנה","order_period":0,"female":{"amount":891,"percentage":15.1},"male":{"amount":1022,"percentage":17.3}},{"section":"90+","period":"שנה","order_period":0,"female":{"amount":568,"percentage":9.6},"male":{"amount":436,"percentage":7.4}}]},{"id":"2","data":[{"section":"0-9","period":"3 חודשים","order_period":0,"female":{"amount":0,"percentage":0.0},"male":{"amount":1,"percentage":0.6}},{"section":"10-19","period":"3 חודשים","order_period":0,"female":{"amount":0,"percentage":0.0},"male":{"amount":0,"percentage":0.0}},{"section":"20-29","period":"3 חודשים","order_period":0,"female":{"amount":0,"percentage":0.0},"male":{"amount":1,"percentage":0.6}},{"section":"30-39","period":"3 חודשים","order_period":0,"female":{"amount":4,"percentage":2.4},"male":{"amount":4,"percentage":2.4}},{"section":"40-49","period":"3 חודשים","order_period":0,"female":{"amount":3,"percentage":1.8},"male":{"amount":13,"percentage":7.8}},{"section":"50-59","period":"3 חודשים","order_period":0,"female":{"amount":11,"percentage":6.6},"male":{"amount":16,"percentage":9.6}},{"section":"60-69","period":"3 חודשים","order_period":0,"female":{"amount":16,"percentage":9.6},"male":{"amount":20,"percentage":12.0}},{"section":"70-79","period":"3 חודשים","order_period":0,"female":{"amount":19,"percentage":11.4},"male":{"amount":23,"percentage":13.8}},{"section":"80-89","period":"3 חודשים","order_period":0,"female":{"amount":15,"percentage":9.0},"male":{"amount":15,"percentage":9.0}},{"section":"90+","period":"3 חודשים","order_period":0,"female":{"amount":1,"percentage":0.6},"male":{"amount":5,"percentage":3.0}},{"section":"0-9","period":"6 חודשים","order_period":0,"female":{"amount":4,"percentage":0.4},"male":{"amount":2,"percentage":0.2}},{"section":"10-19","period":"6 חודשים","order_period":0,"female":{"amount":4,"percentage":0.4},"male":{"amount":1,"percentage":0.1}},{"section":"20-29","period":"6 חודשים","order_period":0,"female":{"amount":11,"percentage":1.0},"male":{"amount":18,"percentage":1.7}},{"section":"30-39","period":"6 חודשים","order_period":0,"female":{"amount":34,"percentage":3.2},"male":{"amount":23,"percentage":2.2}},{"section":"40-49","period":"6 חודשים","order_period":0,"female":{"amount":34,"percentage":3.2},"male":{"amount":65,"percentage":6.2}},{"section":"50-59","period":"6 חודשים","order_period":0,"female":{"amount":64,"percentage":6.1},"male":{"amount":118,"percentage":11.2}},{"section":"60-69","period":"6 חודשים","order_period":0,"female":{"amount":101,"percentage":9.6},"male":{"amount":143,"percentage":13.6}},{"section":"70-79","period":"6 חודשים","order_period":0,"female":{"amount":104,"percentage":9.9},"male":{"amount":145,"percentage":13.8}},{"section":"80-89","period":"6 חודשים","order_period":0,"female":{"amount":73,"percentage":7.0},"male":{"amount":80,"percentage":7.6}},{"section":"90+","period":"6 חודשים","order_period":0,"female":{"amount":11,"percentage":1.0},"male":{"amount":15,"percentage":1.4}},{"section":"0-9","period":"חודש אחרון","order_period":0,"female":{"amount":0,"percentage":0.0},"male":{"amount":1,"percentage":0.9}},{"section":"10-19","period":"חודש אחרון","order_period":0,"female":{"amount":0,"percentage":0.0},"male":{"amount":0,"percentage":0.0}},{"section":"20-29","period":"חודש אחרון","order_period":0,"female":{"amount":0,"percentage":0.0},"male":{"amount":0,"percentage":0.0}},{"section":"30-39","period":"חודש אחרון","order_period":0,"female":{"amount":1,"percentage":0.9},"male":{"amount":2,"percentage":1.8}},{"section":"40-49","period":"חודש אחרון","order_period":0,"female":{"amount":3,"percentage":2.6},"male":{"amount":5,"percentage":4.4}},{"section":"50-59","period":"חודש אחרון","order_period":0,"female":{"amount":4,"percentage":3.5},"male":{"amount":4,"percentage":3.5}},{"section":"60-69","period":"חודש אחרון","order_period":0,"female":{"amount":12,"percentage":10.5},"male":{"amount":16,"percentage":14.0}},{"section":"70-79","period":"חודש אחרון","order_period":0,"female":{"amount":14,"percentage":12.3},"male":{"amount":21,"percentage":18.4}},{"section":"80-89","period":"חודש אחרון","order_period":0,"female":{"amount":13,"percentage":11.4},"male":{"amount":13,"percentage":11.4}},{"section":"90+","period":"חודש אחרון","order_period":0,"female":{"amount":1,"percentage":0.9},"male":{"amount":4,"percentage":3.5}},{"section":"0-9","period":"מתחילת קורונה","order_period":0,"female":{"amount":9,"percentage":0.2},"male":{"amount":8,"percentage":0.2}},{"section":"10-19","period":"מתחילת קורונה","order_period":0,"female":{"amount":9,"percentage":0.2},"male":{"amount":11,"percentage":0.3}},{"section":"20-29","period":"מתחילת קורונה","order_period":0,"female":{"amount":35,"percentage":0.9},"male":{"amount":32,"percentage":0.8}},{"section":"30-39","period":"מתחילת קורונה","order_period":0,"female":{"amount":67,"percentage":1.8},"male":{"amount":60,"percentage":1.6}},{"section":"40-49","period":"מתחילת קורונה","order_period":0,"female":{"amount":87,"percentage":2.3},"male":{"amount":162,"percentage":4.2}},{"section":"50-59","period":"מתחילת קורונה","order_period":0,"female":{"amount":149,"percentage":3.9},"male":{"amount":360,"percentage":9.4}},{"section":"60-69","period":"מתחילת קורונה","order_period":0,"female":{"amount":298,"percentage":7.8},"male":{"amount":644,"percentage":16.8}},{"section":"70-79","period":"מתחילת קורונה","order_period":0,"female":{"amount":357,"percentage":9.3},"male":{"amount":698,"percentage":18.2}},{"section":"80-89","period":"מתחילת קורונה","order_period":0,"female":{"amount":281,"percentage":7.3},"male":{"amount":404,"percentage":10.6}},{"section":"90+","period":"מתחילת קורונה","order_period":0,"female":{"amount":73,"percentage":1.9},"male":{"amount":84,"percentage":2.2}},{"section":"0-9","period":"שנה","order_period":0,"female":{"amount":7,"percentage":0.2},"male":{"amount":6,"percentage":0.2}},{"section":"10-19","period":"שנה","order_period":0,"female":{"amount":7,"percentage":0.2},"male":{"amount":8,"percentage":0.2}},{"section":"20-29","period":"שנה","order_period":0,"female":{"amount":30,"percentage":0.9},"male":{"amount":28,"percentage":0.8}},{"section":"30-39","period":"שנה","order_period":0,"female":{"amount":58,"percentage":1.8},"male":{"amount":46,"percentage":1.4}},{"section":"40-49","period":"שנה","order_period":0,"female":{"amount":78,"percentage":2.4},"male":{"amount":142,"percentage":4.3}},{"section":"50-59","period":"שנה","order_period":0,"female":{"amount":135,"percentage":4.1},"male":{"amount":310,"percentage":9.4}},{"section":"60-69","period":"שנה","order_period":0,"female":{"amount":270,"percentage":8.2},"male":{"amount":560,"percentage":17.0}},{"section":"70-79","period":"שנה","order_period":0,"female":{"amount":318,"percentage":9.6},"male":{"amount":594,"percentage":18.0}},{"section":"80-89","period":"שנה","order_period":0,"female":{"amount":238,"percentage":7.2},"male":{"amount":342,"percentage":10.4}},{"section":"90+","period":"שנה","order_period":0,"female":{"amount":57,"percentage":1.7},"male":{"amount":66,"percentage":2.0}}]},{"id":"3","data":[{"section":"0-9","period":"3 חודשים","order_period":0,"female":{"amount":3,"percentage":0.4},"male":{"amount":2,"percentage":0.2}},{"section":"10-19","period":"3 חודשים","order_period":0,"female":{"amount":3,"percentage":0.4},"male":{"amount":1,"percentage":0.1}},{"section":"20-29","period":"3 חודשים","order_period":0,"female":{"amount":2,"percentage":0.2},"male":{"amount":4,"percentage":0.5}},{"section":"30-39","period":"3 חודשים","order_period":0,"female":{"amount":16,"percentage":1.9},"male":{"amount":14,"percentage":1.6}},{"section":"40-49","period":"3 חודשים","order_period":0,"female":{"amount":20,"percentage":2.3},"male":{"amount":36,"percentage":4.2}},{"section":"50-59","period":"3 חודשים","order_period":0,"female":{"amount":44,"percentage":5.1},"male":{"amount":40,"percentage":4.7}},{"section":"60-69","period":"3 חודשים","order_period":0,"female":{"amount":57,"percentage":6.7},"male":{"amount":98,"percentage":11.4}},{"section":"70-79","period":"3 חודשים","order_period":0,"female":{"amount":93,"percentage":10.9},"male":{"amount":128,"percentage":15.0}},{"section":"80-89","period":"3 חודשים","order_period":0,"female":{"amount":99,"percentage":11.6},"male":{"amount":113,"percentage":13.2}},{"section":"90+","period":"3 חודשים","order_period":0,"female":{"amount":59,"percentage":6.9},"male":{"amount":24,"percentage":2.8}},{"section":"0-9","period":"6 חודשים","order_period":0,"female":{"amount":12,"percentage":0.3},"male":{"amount":8,"percentage":0.2}},{"section":"10-19","period":"6 חודשים","order_period":0,"female":{"amount":17,"percentage":0.4},"male":{"amount":10,"percentage":0.2}},{"section":"20-29","period":"6 חודשים","order_period":0,"female":{"amount":67,"percentage":1.5},"male":{"amount":66,"percentage":1.4}},{"section":"30-39","period":"6 חודשים","order_period":0,"female":{"amount":165,"percentage":3.6},"male":{"amount":155,"percentage":3.4}},{"section":"40-49","period":"6 חודשים","order_period":0,"female":{"amount":218,"percentage":4.8},"male":{"amount":322,"percentage":7.0}},{"section":"50-59","period":"6 חודשים","order_period":0,"female":{"amount":332,"percentage":7.3},"male":{"amount":400,"percentage":8.8}},{"section":"60-69","period":"6 חודשים","order_period":0,"female":{"amount":382,"percentage":8.4},"male":{"amount":454,"percentage":9.9}},{"section":"70-79","period":"6 חודשים","order_period":0,"female":{"amount":432,"percentage":9.5},"male":{"amount":497,"percentage":10.9}},{"section":"80-89","period":"6 חודשים","order_period":0,"female":{"amount":425,"percentage":9.3},"male":{"amount":358,"percentage":7.8}},{"section":"90+","period":"6 חודשים","order_period":0,"female":{"amount":158,"percentage":3.5},"male":{"amount":92,"percentage":2.0}},{"section":"0-9","period":"חודש אחרון","order_period":0,"female":{"amount":2,"percentage":0.3},"male":{"amount":1,"percentage":0.1}},{"section":"10-19","period":"חודש אחרון","order_period":0,"female":{"amount":2,"percentage":0.3},"male":{"amount":1,"percentage":0.1}},{"section":"20-29","period":"חודש אחרון","order_period":0,"female":{"amount":1,"percentage":0.1},"male":{"amount":2,"percentage":0.3}},{"section":"30-39","period":"חודש אחרון","order_period":0,"female":{"amount":12,"percentage":1.6},"male":{"amount":12,"percentage":1.6}},{"section":"40-49","period":"חודש אחרון","order_period":0,"female":{"amount":17,"percentage":2.2},"male":{"amount":33,"percentage":4.3}},{"section":"50-59","period":"חודש אחרון","order_period":0,"female":{"amount":35,"percentage":4.5},"male":{"amount":37,"percentage":4.8}},{"section":"60-69","period":"חודש אחרון","order_period":0,"female":{"amount":46,"percentage":6.0},"male":{"amount":90,"percentage":11.7}},{"section":"70-79","period":"חודש אחרון","order_period":0,"female":{"amount":85,"percentage":11.0},"male":{"amount":124,"percentage":16.1}},{"section":"80-89","period":"חודש אחרון","order_period":0,"female":{"amount":92,"percentage":11.9},"male":{"amount":103,"percentage":13.3}},{"section":"90+","period":"חודש אחרון","order_period":0,"female":{"amount":55,"percentage":7.1},"male":{"amount":22,"percentage":2.8}},{"section":"0-9","period":"מתחילת קורונה","order_period":0,"female":{"amount":24,"percentage":0.1},"male":{"amount":26,"percentage":0.1}},{"section":"10-19","period":"מתחילת קורונה","order_period":0,"female":{"amount":46,"percentage":0.3},"male":{"amount":29,"percentage":0.2}},{"section":"20-29","period":"מתחילת קורונה","order_period":0,"female":{"amount":162,"percentage":0.9},"male":{"amount":142,"percentage":0.8}},{"section":"30-39","period":"מתחילת קורונה","order_period":0,"female":{"amount":362,"percentage":2.1},"male":{"amount":412,"percentage":2.3}},{"section":"40-49","period":"מתחילת קורונה","order_period":0,"female":{"amount":596,"percentage":3.4},"male":{"amount":964,"percentage":5.5}},{"section":"50-59","period":"מתחילת קורונה","order_period":0,"female":{"amount":1014,"percentage":5.7},"male":{"amount":1565,"percentage":8.9}},{"section":"60-69","period":"מתחילת קורונה","order_period":0,"female":{"amount":1367,"percentage":7.7},"male":{"amount":2202,"percentage":12.5}},{"section":"70-79","period":"מתחילת קורונה","order_period":0,"female":{"amount":1645,"percentage":9.3},"male":{"amount":2344,"percentage":13.3}},{"section":"80-89","period":"מתחילת קורונה","order_period":0,"female":{"amount":1710,"percentage":9.7},"male":{"amount":1678,"percentage":9.5}},{"section":"90+","period":"מתחילת קורונה","order_period":0,"female":{"amount":819,"percentage":4.6},"male":{"amount":536,"percentage":3.0}},{"section":"0-9","period":"שנה","order_period":0,"female":{"amount":20,"percentage":0.1},"male":{"amount":24,"percentage":0.1}},{"section":"10-19","period":"שנה","order_period":0,"female":{"amount":43,"percentage":0.3},"male":{"amount":27,"percentage":0.2}},{"section":"20-29","period":"שנה","order_period":0,"female":{"amount":152,"percentage":0.9},"male":{"amount":132,"percentage":0.8}},{"section":"30-39","period":"שנה","order_period":0,"female":{"amount":334,"percentage":2.1},"male":{"amount":368,"percentage":2.3}},{"section":"40-49","period":"שנה","order_period":0,"female":{"amount":552,"percentage":3.4},"male":{"amount":891,"percentage":5.5}},{"section":"50-59","period":"שנה","order_period":0,"female":{"amount":940,"percentage":5.8},"male":{"amount":1431,"percentage":8.9}},{"section":"60-69","period":"שנה","order_period":0,"female":{"amount":1274,"percentage":7.9},"male":{"amount":2011,"percentage":12.5}},{"section":"70-79","period":"שנה","order_period":0,"female":{"amount":1518,"percentage":9.4},"male":{"amount":2111,"percentage":13.1}},{"section":"80-89","period":"שנה","order_period":0,"female":{"amount":1536,"percentage":9.5},"male":{"amount":1535,"percentage":9.5}},{"section":"90+","period":"שנה","order_period":0,"female":{"amount":724,"percentage":4.5},"male":{"amount":475,"percentage":3.0}}]}]