[{"id":"0","data":[{"section":"0-9","male":{"amount":349233,"percentage":10.8},"female":{"amount":284146,"percentage":8.8},"period":"שנה"},{"section":"0-9","male":{"amount":4809,"percentage":6},"female":{"amount":4049,"percentage":5.1},"period":"חודש אחרון"},{"section":"0-9","female":{"amount":219606,"percentage":8},"male":{"amount":278673,"percentage":10.1},"period":"6 חודשים"},{"section":"0-9","male":{"amount":47609,"percentage":7.9},"female":{"amount":37604,"percentage":6.2},"period":"3 חודשים"},{"section":"0-9","female":{"amount":342149,"percentage":8.4},"male":{"amount":417612,"percentage":10.3},"period":"מתחילת קורונה"},{"section":"10-19","male":{"amount":321204,"percentage":9.9},"female":{"amount":322029,"percentage":9.9},"period":"שנה"},{"section":"10-19","female":{"amount":407169,"percentage":10},"male":{"amount":417492,"percentage":10.2},"period":"מתחילת קורונה"},{"section":"10-19","male":{"amount":269285,"percentage":9.8},"female":{"amount":268592,"percentage":9.8},"period":"6 חודשים"},{"section":"10-19","male":{"amount":41261,"percentage":6.8},"female":{"amount":41461,"percentage":6.9},"period":"3 חודשים"},{"section":"10-19","male":{"amount":3790,"percentage":4.8},"female":{"amount":4128,"percentage":5.2},"period":"חודש אחרון"},{"section":"20-29","female":{"amount":265460,"percentage":8.2},"male":{"amount":173916,"percentage":5.4},"period":"שנה"},{"section":"20-29","female":{"amount":47085,"percentage":7.8},"male":{"amount":31286,"percentage":5.2},"period":"3 חודשים"},{"section":"20-29","female":{"amount":4845,"percentage":6.1},"male":{"amount":3184,"percentage":4},"period":"חודש אחרון"},{"section":"20-29","male":{"amount":144827,"percentage":5.3},"female":{"amount":227194,"percentage":8.3},"period":"6 חודשים"},{"section":"20-29","male":{"amount":244464,"percentage":6},"female":{"amount":349376,"percentage":8.6},"period":"מתחילת קורונה"},{"section":"30-39","female":{"amount":286252,"percentage":8.8},"male":{"amount":186221,"percentage":5.7},"period":"שנה"},{"section":"30-39","female":{"amount":6621,"percentage":8.3},"male":{"amount":4683,"percentage":5.9},"period":"חודש אחרון"},{"section":"30-39","male":{"amount":157670,"percentage":5.7},"female":{"amount":245501,"percentage":8.9},"period":"6 חודשים"},{"section":"30-39","female":{"amount":54428,"percentage":9},"male":{"amount":38509,"percentage":6.4},"period":"3 חודשים"},{"section":"30-39","male":{"amount":238797,"percentage":5.9},"female":{"amount":348707,"percentage":8.6},"period":"מתחילת קורונה"},{"section":"40-49","male":{"amount":170018,"percentage":5.2},"female":{"amount":253948,"percentage":7.8},"period":"שנה"},{"section":"40-49","female":{"amount":6550,"percentage":8.2},"male":{"amount":4652,"percentage":5.8},"period":"חודש אחרון"},{"section":"40-49","male":{"amount":146882,"percentage":5.3},"female":{"amount":224114,"percentage":8.2},"period":"6 חודשים"},{"section":"40-49","female":{"amount":52637,"percentage":8.7},"male":{"amount":35836,"percentage":5.9},"period":"3 חודשים"},{"section":"40-49","male":{"amount":214030,"percentage":5.3},"female":{"amount":308149,"percentage":7.6},"period":"מתחילת קורונה"},{"section":"50-59","male":{"amount":111645,"percentage":3.4},"female":{"amount":166220,"percentage":5.1},"period":"שנה"},{"section":"50-59","female":{"amount":149762,"percentage":5.5},"male":{"amount":98744,"percentage":3.6},"period":"6 חודשים"},{"section":"50-59","female":{"amount":6024,"percentage":7.6},"male":{"amount":3773,"percentage":4.7},"period":"חודש אחרון"},{"section":"50-59","male":{"amount":144335,"percentage":3.5},"female":{"amount":205067,"percentage":5},"period":"מתחילת קורונה"},{"section":"50-59","female":{"amount":41559,"percentage":6.9},"male":{"amount":26376,"percentage":4.4},"period":"3 חודשים"},{"section":"60-69","male":{"amount":79571,"percentage":2.5},"female":{"amount":112201,"percentage":3.5},"period":"שנה"},{"section":"60-69","female":{"amount":6311,"percentage":7.9},"male":{"amount":4010,"percentage":5},"period":"חודש אחרון"},{"section":"60-69","male":{"amount":71300,"percentage":2.6},"female":{"amount":102107,"percentage":3.7},"period":"6 חודשים"},{"section":"60-69","female":{"amount":33465,"percentage":5.5},"male":{"amount":22047,"percentage":3.6},"period":"3 חודשים"},{"section":"60-69","male":{"amount":101927,"percentage":2.5},"female":{"amount":136022,"percentage":3.3},"period":"מתחילת קורונה"},{"section":"70-79","female":{"amount":53386,"percentage":1.9},"male":{"amount":42941,"percentage":1.6},"period":"6 חודשים"},{"section":"70-79","female":{"amount":58790,"percentage":1.8},"male":{"amount":47421,"percentage":1.5},"period":"שנה"},{"section":"70-79","female":{"amount":70809,"percentage":1.7},"male":{"amount":58567,"percentage":1.4},"period":"מתחילת קורונה"},{"section":"70-79","female":{"amount":20587,"percentage":3.4},"male":{"amount":16159,"percentage":2.7},"period":"3 חודשים"},{"section":"70-79","male":{"amount":3642,"percentage":4.6},"female":{"amount":4657,"percentage":5.8},"period":"חודש אחרון"},{"section":"80-89","male":{"amount":17279,"percentage":0.5},"female":{"amount":24346,"percentage":0.8},"period":"שנה"},{"section":"80-89","male":{"amount":15252,"percentage":0.6},"female":{"amount":21639,"percentage":0.8},"period":"6 חודשים"},{"section":"80-89","female":{"amount":7843,"percentage":1.3},"male":{"amount":5735,"percentage":0.9},"period":"3 חודשים"},{"section":"80-89","female":{"amount":1881,"percentage":2.4},"male":{"amount":1323,"percentage":1.7},"period":"חודש אחרון"},{"section":"80-89","male":{"amount":22302,"percentage":0.5},"female":{"amount":31578,"percentage":0.8},"period":"מתחילת קורונה"},{"section":"90+","male":{"amount":3652,"percentage":0.1},"female":{"amount":7014,"percentage":0.2},"period":"שנה"},{"section":"90+","male":{"amount":3211,"percentage":0.1},"female":{"amount":6196,"percentage":0.2},"period":"6 חודשים"},{"section":"90+","male":{"amount":1108,"percentage":0.2},"female":{"amount":2058,"percentage":0.3},"period":"3 חודשים"},{"section":"90+","male":{"amount":264,"percentage":0.3},"female":{"amount":540,"percentage":0.7},"period":"חודש אחרון"},{"section":"90+","female":{"amount":9810,"percentage":0.2},"male":{"amount":4930,"percentage":0.1},"period":"מתחילת קורונה"}]},{"id":"1","data":[{"section":"0-9","male":{"amount":5,"percentage":0.1},"female":{"amount":2,"percentage":0},"period":"שנה"},{"section":"0-9","male":{"amount":0,"percentage":0},"female":{"amount":0,"percentage":0},"period":"חודש אחרון"},{"section":"0-9","female":{"amount":2,"percentage":0.1},"male":{"amount":4,"percentage":0.2},"period":"6 חודשים"},{"section":"0-9","male":{"amount":0,"percentage":0},"female":{"amount":1,"percentage":0.1},"period":"3 חודשים"},{"section":"0-9","female":{"amount":5,"percentage":0},"male":{"amount":7,"percentage":0.1},"period":"מתחילת קורונה"},{"section":"10-19","male":{"amount":5,"percentage":0.1},"female":{"amount":5,"percentage":0.1},"period":"שנה"},{"section":"10-19","female":{"amount":8,"percentage":0.1},"male":{"amount":7,"percentage":0.1},"period":"מתחילת קורונה"},{"section":"10-19","male":{"amount":4,"percentage":0.2},"female":{"amount":3,"percentage":0.1},"period":"6 חודשים"},{"section":"10-19","male":{"amount":1,"percentage":0.1},"female":{"amount":1,"percentage":0.1},"period":"3 חודשים"},{"section":"10-19","male":{"amount":0,"percentage":0},"female":{"amount":1,"percentage":0.8},"period":"חודש אחרון"},{"section":"20-29","female":{"amount":9,"percentage":0.2},"male":{"amount":5,"percentage":0.1},"period":"שנה"},{"section":"20-29","female":{"amount":0,"percentage":0},"male":{"amount":1,"percentage":0.1},"period":"3 חודשים"},{"section":"20-29","female":{"amount":0,"percentage":0},"male":{"amount":0,"percentage":0},"period":"חודש אחרון"},{"section":"20-29","male":{"amount":2,"percentage":0.1},"female":{"amount":6,"percentage":0.2},"period":"6 חודשים"},{"section":"20-29","male":{"amount":24,"percentage":0.2},"female":{"amount":22,"percentage":0.2},"period":"מתחילת קורונה"},{"section":"30-39","female":{"amount":17,"percentage":0.4},"male":{"amount":25,"percentage":0.6},"period":"שנה"},{"section":"30-39","female":{"amount":1,"percentage":0.8},"male":{"amount":0,"percentage":0},"period":"חודש אחרון"},{"section":"30-39","male":{"amount":12,"percentage":0.5},"female":{"amount":6,"percentage":0.2},"period":"6 חודשים"},{"section":"30-39","female":{"amount":3,"percentage":0.3},"male":{"amount":4,"percentage":0.4},"period":"3 חודשים"},{"section":"30-39","male":{"amount":53,"percentage":0.5},"female":{"amount":38,"percentage":0.4},"period":"מתחילת קורונה"},{"section":"40-49","male":{"amount":52,"percentage":1.2},"female":{"amount":21,"percentage":0.5},"period":"שנה"},{"section":"40-49","female":{"amount":1,"percentage":0.8},"male":{"amount":0,"percentage":0},"period":"חודש אחרון"},{"section":"40-49","male":{"amount":21,"percentage":0.8},"female":{"amount":12,"percentage":0.5},"period":"6 חודשים"},{"section":"40-49","female":{"amount":3,"percentage":0.3},"male":{"amount":5,"percentage":0.6},"period":"3 חודשים"},{"section":"40-49","male":{"amount":120,"percentage":1.1},"female":{"amount":77,"percentage":0.7},"period":"מתחילת קורונה"},{"section":"50-59","male":{"amount":136,"percentage":3.1},"female":{"amount":78,"percentage":1.8},"period":"שנה"},{"section":"50-59","female":{"amount":41,"percentage":1.6},"male":{"amount":71,"percentage":2.7},"period":"6 חודשים"},{"section":"50-59","female":{"amount":1,"percentage":0.8},"male":{"amount":7,"percentage":5.4},"period":"חודש אחרון"},{"section":"50-59","male":{"amount":387,"percentage":3.6},"female":{"amount":199,"percentage":1.8},"period":"מתחילת קורונה"},{"section":"50-59","female":{"amount":11,"percentage":1.2},"male":{"amount":27,"percentage":3},"period":"3 חודשים"},{"section":"60-69","male":{"amount":353,"percentage":8},"female":{"amount":252,"percentage":5.7},"period":"שנה"},{"section":"60-69","female":{"amount":4,"percentage":3.1},"male":{"amount":3,"percentage":2.3},"period":"חודש אחרון"},{"section":"60-69","male":{"amount":181,"percentage":6.9},"female":{"amount":111,"percentage":4.2},"period":"6 חודשים"},{"section":"60-69","female":{"amount":48,"percentage":5.3},"male":{"amount":68,"percentage":7.6},"period":"3 חודשים"},{"section":"60-69","male":{"amount":995,"percentage":9.2},"female":{"amount":554,"percentage":5.1},"period":"מתחילת קורונה"},{"section":"70-79","female":{"amount":252,"percentage":9.5},"male":{"amount":346,"percentage":13.1},"period":"6 חודשים"},{"section":"70-79","female":{"amount":437,"percentage":9.9},"male":{"amount":605,"percentage":13.7},"period":"שנה"},{"section":"70-79","female":{"amount":1035,"percentage":9.6},"male":{"amount":1634,"percentage":15.1},"period":"מתחילת קורונה"},{"section":"70-79","female":{"amount":93,"percentage":10.3},"male":{"amount":120,"percentage":13.3},"period":"3 חודשים"},{"section":"70-79","male":{"amount":12,"percentage":9.3},"female":{"amount":17,"percentage":13.2},"period":"חודש אחרון"},{"section":"80-89","male":{"amount":786,"percentage":17.9},"female":{"amount":749,"percentage":17},"period":"שנה"},{"section":"80-89","male":{"amount":497,"percentage":18.8},"female":{"amount":476,"percentage":18},"period":"6 חודשים"},{"section":"80-89","female":{"amount":148,"percentage":16.5},"male":{"amount":163,"percentage":18.1},"period":"3 חודשים"},{"section":"80-89","female":{"amount":24,"percentage":18.6},"male":{"amount":14,"percentage":10.9},"period":"חודש אחרון"},{"section":"80-89","male":{"amount":1901,"percentage":17.6},"female":{"amount":1741,"percentage":16.1},"period":"מתחילת קורונה"},{"section":"90+","male":{"amount":379,"percentage":8.6},"female":{"amount":480,"percentage":10.9},"period":"שנה"},{"section":"90+","male":{"amount":278,"percentage":10.5},"female":{"amount":317,"percentage":12},"period":"6 חודשים"},{"section":"90+","male":{"amount":100,"percentage":11.1},"female":{"amount":102,"percentage":11.3},"period":"3 חודשים"},{"section":"90+","male":{"amount":16,"percentage":12.4},"female":{"amount":28,"percentage":21.7},"period":"חודש אחרון"},{"section":"90+","female":{"amount":1144,"percentage":10.6},"male":{"amount":868,"percentage":8},"period":"מתחילת קורונה"}]},{"id":"2","data":[{"section":"0-9","male":{"amount":23,"percentage":1},"female":{"amount":8,"percentage":0.3},"period":"שנה"},{"section":"0-9","male":{"amount":1,"percentage":0.7},"female":{"amount":0,"percentage":0},"period":"חודש אחרון"},{"section":"0-9","female":{"amount":8,"percentage":0.6},"male":{"amount":17,"percentage":1.2},"period":"6 חודשים"},{"section":"0-9","male":{"amount":8,"percentage":1.2},"female":{"amount":4,"percentage":0.6},"period":"3 חודשים"},{"section":"0-9","female":{"amount":15,"percentage":0.2},"male":{"amount":31,"percentage":0.5},"period":"מתחילת קורונה"},{"section":"10-19","male":{"amount":14,"percentage":0.6},"female":{"amount":16,"percentage":0.7},"period":"שנה"},{"section":"10-19","female":{"amount":24,"percentage":0.4},"male":{"amount":23,"percentage":0.4},"period":"מתחילת קורונה"},{"section":"10-19","male":{"amount":9,"percentage":0.6},"female":{"amount":10,"percentage":0.7},"period":"6 חודשים"},{"section":"10-19","male":{"amount":4,"percentage":0.6},"female":{"amount":3,"percentage":0.4},"period":"3 חודשים"},{"section":"10-19","male":{"amount":0,"percentage":0},"female":{"amount":2,"percentage":1.3},"period":"חודש אחרון"},{"section":"20-29","female":{"amount":20,"percentage":0.8},"male":{"amount":22,"percentage":0.9},"period":"שנה"},{"section":"20-29","female":{"amount":1,"percentage":0.1},"male":{"amount":5,"percentage":0.7},"period":"3 חודשים"},{"section":"20-29","female":{"amount":1,"percentage":0.7},"male":{"amount":0,"percentage":0},"period":"חודש אחרון"},{"section":"20-29","male":{"amount":11,"percentage":0.8},"female":{"amount":14,"percentage":1},"period":"6 חודשים"},{"section":"20-29","male":{"amount":54,"percentage":0.9},"female":{"amount":57,"percentage":0.9},"period":"מתחילת קורונה"},{"section":"30-39","female":{"amount":38,"percentage":1.6},"male":{"amount":48,"percentage":2},"period":"שנה"},{"section":"30-39","female":{"amount":3,"percentage":2},"male":{"amount":4,"percentage":2.7},"period":"חודש אחרון"},{"section":"30-39","male":{"amount":29,"percentage":2.1},"female":{"amount":18,"percentage":1.3},"period":"6 חודשים"},{"section":"30-39","female":{"amount":12,"percentage":1.8},"male":{"amount":20,"percentage":3},"period":"3 חודשים"},{"section":"30-39","male":{"amount":102,"percentage":1.7},"female":{"amount":105,"percentage":1.7},"period":"מתחילת קורונה"},{"section":"40-49","male":{"amount":105,"percentage":4.4},"female":{"amount":51,"percentage":2.1},"period":"שנה"},{"section":"40-49","female":{"amount":5,"percentage":3.3},"male":{"amount":5,"percentage":3.3},"period":"חודש אחרון"},{"section":"40-49","male":{"amount":54,"percentage":3.8},"female":{"amount":22,"percentage":1.6},"period":"6 חודשים"},{"section":"40-49","female":{"amount":9,"percentage":1.3},"male":{"amount":18,"percentage":2.7},"period":"3 חודשים"},{"section":"40-49","male":{"amount":261,"percentage":4.3},"female":{"amount":139,"percentage":2.3},"period":"מתחילת קורונה"},{"section":"50-59","male":{"amount":194,"percentage":8.1},"female":{"amount":113,"percentage":4.7},"period":"שנה"},{"section":"50-59","female":{"amount":59,"percentage":4.2},"male":{"amount":110,"percentage":7.8},"period":"6 חודשים"},{"section":"50-59","female":{"amount":5,"percentage":3.3},"male":{"amount":17,"percentage":11.3},"period":"חודש אחרון"},{"section":"50-59","male":{"amount":546,"percentage":9.1},"female":{"amount":255,"percentage":4.2},"period":"מתחילת קורונה"},{"section":"50-59","female":{"amount":19,"percentage":2.8},"male":{"amount":55,"percentage":8.2},"period":"3 חודשים"},{"section":"60-69","male":{"amount":296,"percentage":12.4},"female":{"amount":209,"percentage":8.8},"period":"שנה"},{"section":"60-69","female":{"amount":12,"percentage":8},"male":{"amount":19,"percentage":12.7},"period":"חודש אחרון"},{"section":"60-69","male":{"amount":168,"percentage":11.9},"female":{"amount":98,"percentage":7},"period":"6 חודשים"},{"section":"60-69","female":{"amount":55,"percentage":8.2},"male":{"amount":94,"percentage":14},"period":"3 חודשים"},{"section":"60-69","male":{"amount":925,"percentage":15.3},"female":{"amount":503,"percentage":8.3},"period":"מתחילת קורונה"},{"section":"70-79","female":{"amount":145,"percentage":10.3},"male":{"amount":224,"percentage":15.9},"period":"6 חודשים"},{"section":"70-79","female":{"amount":248,"percentage":10.4},"male":{"amount":366,"percentage":15.4},"period":"שנה"},{"section":"70-79","female":{"amount":582,"percentage":9.6},"male":{"amount":1018,"percentage":16.9},"period":"מתחילת קורונה"},{"section":"70-79","female":{"amount":66,"percentage":9.8},"male":{"amount":114,"percentage":16.9},"period":"3 חודשים"},{"section":"70-79","male":{"amount":28,"percentage":18.7},"female":{"amount":15,"percentage":10},"period":"חודש אחרון"},{"section":"80-89","male":{"amount":262,"percentage":11},"female":{"amount":222,"percentage":9.3},"period":"שנה"},{"section":"80-89","male":{"amount":177,"percentage":12.6},"female":{"amount":142,"percentage":10.1},"period":"6 חודשים"},{"section":"80-89","female":{"amount":65,"percentage":9.7},"male":{"amount":83,"percentage":12.3},"period":"3 חודשים"},{"section":"80-89","female":{"amount":8,"percentage":5.3},"male":{"amount":17,"percentage":11.3},"period":"חודש אחרון"},{"section":"80-89","male":{"amount":637,"percentage":10.6},"female":{"amount":476,"percentage":7.9},"period":"מתחילת קורונה"},{"section":"90+","male":{"amount":63,"percentage":2.6},"female":{"amount":65,"percentage":2.7},"period":"שנה"},{"section":"90+","male":{"amount":46,"percentage":3.3},"female":{"amount":48,"percentage":3.4},"period":"6 חודשים"},{"section":"90+","male":{"amount":18,"percentage":2.7},"female":{"amount":20,"percentage":3},"period":"3 חודשים"},{"section":"90+","male":{"amount":3,"percentage":2},"female":{"amount":5,"percentage":3.3},"period":"חודש אחרון"},{"section":"90+","female":{"amount":138,"percentage":2.3},"male":{"amount":141,"percentage":2.3},"period":"מתחילת קורונה"}]},{"id":"3","data":[{"section":"0-9","male":{"amount":80,"percentage":0.7},"female":{"amount":55,"percentage":0.5},"period":"שנה"},{"section":"0-9","male":{"amount":3,"percentage":0.7},"female":{"amount":3,"percentage":0.7},"period":"חודש אחרון"},{"section":"0-9","female":{"amount":37,"percentage":0.5},"male":{"amount":54,"percentage":0.8},"period":"6 חודשים"},{"section":"0-9","male":{"amount":19,"percentage":0.8},"female":{"amount":14,"percentage":0.6},"period":"3 חודשים"},{"section":"0-9","female":{"amount":73,"percentage":0.3},"male":{"amount":111,"percentage":0.4},"period":"מתחילת קורונה"},{"section":"10-19","male":{"amount":41,"percentage":0.3},"female":{"amount":35,"percentage":0.3},"period":"שנה"},{"section":"10-19","female":{"amount":78,"percentage":0.3},"male":{"amount":77,"percentage":0.3},"period":"מתחילת קורונה"},{"section":"10-19","male":{"amount":26,"percentage":0.4},"female":{"amount":17,"percentage":0.3},"period":"6 חודשים"},{"section":"10-19","male":{"amount":6,"percentage":0.2},"female":{"amount":8,"percentage":0.3},"period":"3 חודשים"},{"section":"10-19","male":{"amount":1,"percentage":0.2},"female":{"amount":2,"percentage":0.4},"period":"חודש אחרון"},{"section":"20-29","female":{"amount":98,"percentage":0.8},"male":{"amount":91,"percentage":0.8},"period":"שנה"},{"section":"20-29","female":{"amount":4,"percentage":0.2},"male":{"amount":14,"percentage":0.6},"period":"3 חודשים"},{"section":"20-29","female":{"amount":0,"percentage":0},"male":{"amount":4,"percentage":0.9},"period":"חודש אחרון"},{"section":"20-29","male":{"amount":40,"percentage":0.6},"female":{"amount":27,"percentage":0.4},"period":"6 חודשים"},{"section":"20-29","male":{"amount":241,"percentage":0.8},"female":{"amount":272,"percentage":0.9},"period":"מתחילת קורונה"},{"section":"30-39","female":{"amount":222,"percentage":1.8},"male":{"amount":217,"percentage":1.8},"period":"שנה"},{"section":"30-39","female":{"amount":6,"percentage":1.3},"male":{"amount":2,"percentage":0.4},"period":"חודש אחרון"},{"section":"30-39","male":{"amount":61,"percentage":0.9},"female":{"amount":71,"percentage":1},"period":"6 חודשים"},{"section":"30-39","female":{"amount":22,"percentage":0.9},"male":{"amount":20,"percentage":0.8},"period":"3 חודשים"},{"section":"30-39","male":{"amount":626,"percentage":2.2},"female":{"amount":593,"percentage":2.1},"period":"מתחילת קורונה"},{"section":"40-49","male":{"amount":463,"percentage":3.8},"female":{"amount":334,"percentage":2.8},"period":"שנה"},{"section":"40-49","female":{"amount":5,"percentage":1.1},"male":{"amount":9,"percentage":2},"period":"חודש אחרון"},{"section":"40-49","male":{"amount":144,"percentage":2.1},"female":{"amount":90,"percentage":1.3},"period":"6 חודשים"},{"section":"40-49","female":{"amount":28,"percentage":1.1},"male":{"amount":45,"percentage":1.8},"period":"3 חודשים"},{"section":"40-49","male":{"amount":1399,"percentage":4.8},"female":{"amount":967,"percentage":3.4},"period":"מתחילת קורונה"},{"section":"50-59","male":{"amount":708,"percentage":5.9},"female":{"amount":528,"percentage":4.4},"period":"שנה"},{"section":"50-59","female":{"amount":206,"percentage":3},"male":{"amount":301,"percentage":4.4},"period":"6 חודשים"},{"section":"50-59","female":{"amount":10,"percentage":2.2},"male":{"amount":17,"percentage":3.7},"period":"חודש אחרון"},{"section":"50-59","male":{"amount":2222,"percentage":7.7},"female":{"amount":1569,"percentage":5.4},"period":"מתחילת קורונה"},{"section":"50-59","female":{"amount":58,"percentage":2.4},"male":{"amount":104,"percentage":4.3},"period":"3 חודשים"},{"section":"60-69","male":{"amount":1170,"percentage":9.7},"female":{"amount":879,"percentage":7.3},"period":"שנה"},{"section":"60-69","female":{"amount":32,"percentage":7},"male":{"amount":37,"percentage":8.1},"period":"חודש אחרון"},{"section":"60-69","male":{"amount":601,"percentage":8.8},"female":{"amount":430,"percentage":6.3},"period":"6 חודשים"},{"section":"60-69","female":{"amount":159,"percentage":6.5},"male":{"amount":211,"percentage":8.7},"period":"3 חודשים"},{"section":"60-69","male":{"amount":3265,"percentage":11.3},"female":{"amount":2212,"percentage":7.7},"period":"מתחילת קורונה"},{"section":"70-79","female":{"amount":714,"percentage":10.5},"male":{"amount":946,"percentage":13.9},"period":"6 חודשים"},{"section":"70-79","female":{"amount":1211,"percentage":10},"male":{"amount":1537,"percentage":12.7},"period":"שנה"},{"section":"70-79","female":{"amount":2778,"percentage":9.6},"male":{"amount":3649,"percentage":12.6},"period":"מתחילת קורונה"},{"section":"70-79","female":{"amount":260,"percentage":10.7},"male":{"amount":352,"percentage":14.4},"period":"3 חודשים"},{"section":"70-79","male":{"amount":65,"percentage":14.2},"female":{"amount":38,"percentage":8.3},"period":"חודש אחרון"},{"section":"80-89","male":{"amount":1516,"percentage":12.5},"female":{"amount":1566,"percentage":12.9},"period":"שנה"},{"section":"80-89","male":{"amount":1010,"percentage":14.9},"female":{"amount":1044,"percentage":15.4},"period":"6 חודשים"},{"section":"80-89","female":{"amount":345,"percentage":14.1},"male":{"amount":383,"percentage":15.7},"period":"3 חודשים"},{"section":"80-89","female":{"amount":64,"percentage":13.9},"male":{"amount":63,"percentage":13.7},"period":"חודש אחרון"},{"section":"80-89","male":{"amount":3031,"percentage":10.5},"female":{"amount":3143,"percentage":10.9},"period":"מתחילת קורונה"},{"section":"90+","male":{"amount":549,"percentage":4.5},"female":{"amount":797,"percentage":6.6},"period":"שנה"},{"section":"90+","male":{"amount":427,"percentage":6.3},"female":{"amount":551,"percentage":8.1},"period":"6 חודשים"},{"section":"90+","male":{"amount":187,"percentage":7.7},"female":{"amount":200,"percentage":8.2},"period":"3 חודשים"},{"section":"90+","male":{"amount":45,"percentage":9.8},"female":{"amount":53,"percentage":11.5},"period":"חודש אחרון"},{"section":"90+","female":{"amount":1517,"percentage":5.3},"male":{"amount":1024,"percentage":3.5},"period":"מתחילת קורונה"}]}]